Workbook

Sheet Cleaned data
A1: ticker | B1: name | C1: currency | D1: exchange | E1: industry | F1: environment_grade | G1: environment_level | H1: social_grade | I1: social_level | J1: governance_grade | K1: governance_level | L1: environment_score | M1: social_score | N1: governance_score | O1: total_score | P1: last_processing_date | Q1: total_grade | R1: total_level | S1: cik
A2: hei | B2: HEICO Corp | C2: USD | D2: NEW YORK STOCK EXCHANGE, INC. | E2: Aerospace and Defense | F2: B | G2: Medium | H2: B | I2: Medium | J2: B | K2: Medium | L2: 225 | M2: 203 | N2: 205 | O2: 633 | P2: 44872 | Q2: B | R2: Medium | S2: 46619
A3: rtx | B3: Raytheon Technologies Corp | C3: USD | D3: NEW YORK STOCK EXCHANGE, INC. | E3: Aerospace and Defense | F3: A | G3: High | H3: BB | I3: Medium | J3: BBB | K3: High | L3: 520 | M3: 330 | N3: 400 | O3: 1250 | P3: 44723 | Q3: A | R3: High | S3: 101829
A4: hii | B4: Huntington Ingalls Industries Inc | C4: USD | D4: NEW YORK STOCK EXCHANGE, INC. | E4: Aerospace and Defense | F4: A | G4: High | H4: BB | I4: Medium | J4: BB | K4: Medium | L4: 545 | M4: 315 | N4: 315 | O4: 1175 | P4: 44668 | Q4: BBB | R4: High | S4: 1501585
A5: hwm | B5: Howmet Aerospace Inc | C5: USD | D5: NEW YORK STOCK EXCHANGE, INC. | E5: Aerospace and Defense | F5: A | G5: High | H5: BB | I5: Medium | J5: BB | K5: Medium | L5: 525 | M5: 315 | N5: 320 | O5: 1160 | P5: 44722 | Q5: BBB | R5: High | S5: 4281
A6: lmt | B6: Lockheed Martin Corp | C6: USD | D6: NEW YORK STOCK EXCHANGE, INC. | E6: Aerospace and Defense | F6: A | G6: High | H6: BB | I6: Medium | J6: BB | K6: Medium | L6: 510 | M6: 324 | N6: 320 | O6: 1154 | P6: 44669 | Q6: BBB | R6: High | S6: 936468
A7: spr | B7: Spirit AeroSystems Holdings Inc | C7: USD | D7: NEW YORK STOCK EXCHANGE, INC. | E7: Aerospace and Defense | F7: A | G7: High | H7: BB | I7: Medium | J7: BB | K7: Medium | L7: 515 | M7: 337 | N7: 300 | O7: 1152 | P7: 44670 | Q7: BBB | R7: High | S7: 1364885
A8: gd | B8: General Dynamics Corp | C8: USD | D8: NEW YORK STOCK EXCHANGE, INC. | E8: Aerospace and Defense | F8: A | G8: High | H8: BB | I8: Medium | J8: BB | K8: Medium | L8: 510 | M8: 310 | N8: 300 | O8: 1120 | P8: 44723 | Q8: BBB | R8: High | S8: 40533
A9: noc | B9: Northrop Grumman Corp | C9: USD | D9: NEW YORK STOCK EXCHANGE, INC. | E9: Aerospace and Defense | F9: A | G9: High | H9: BB | I9: Medium | J9: BB | K9: Medium | L9: 505 | M9: 302 | N9: 300 | O9: 1107 | P9: 44669 | Q9: BBB | R9: High | S9: 1133421
A10: tdg | B10: TransDigm Group Inc | C10: USD | D10: NEW YORK STOCK EXCHANGE, INC. | E10: Aerospace and Defense | F10: A | G10: High | H10: BB | I10: Medium | J10: BB | K10: Medium | L10: 500 | M10: 300 | N10: 300 | O10: 1100 | P10: 44670 | Q10: BBB | R10: High | S10: 1260221
A11: txt | B11: Textron Inc | C11: USD | D11: NEW YORK STOCK EXCHANGE, INC. | E11: Aerospace and Defense | F11: A | G11: High | H11: BB | I11: Medium | J11: B | K11: Medium | L11: 500 | M11: 300 | N11: 200 | O11: 1000 | P11: 44821 | Q11: BBB | R11: High | S11: 217346
A12: ba | B12: Boeing Co | C12: USD | D12: NEW YORK STOCK EXCHANGE, INC. | E12: Aerospace and Defense | F12: B | G12: Medium | H12: B | I12: Medium | J12: B | K12: Medium | L12: 220 | M12: 224 | N12: 235 | O12: 679 | P12: 44825 | Q12: B | R12: Medium | S12: 12927
A13: dal | B13: Delta Air Lines Inc | C13: USD | D13: NEW YORK STOCK EXCHANGE, INC. | E13: Airlines | F13: A | G13: High | H13: BB | I13: Medium | J13: BB | K13: Medium | L13: 515 | M13: 300 | N13: 313 | O13: 1128 | P13: 44668 | Q13: BBB | R13: High | S13: 27904
... A711: xel | B711: Xcel Energy Inc | C711: USD | D711: NASDAQ NMS - GLOBAL MARKET | E711: Utilities | F711: B | G711: Medium | H711: B | I711: Medium | J711: B | K711: Medium | L711: 223 | M711: 201 | N711: 205 | O711: 629 | P711: 44671 | Q711: B | R711: Medium | S711: 72903

Sheet Summary stats
A1: number_of_companies | B1: industry | C1: E_min_score | D1: E_max_score | E1: E_median_score | F1: S_min_score | G1: S_max_score | H1: S_median_score | I1: G_min_score | J1: G_max_score | K1: G_median_score | L1: Total_min_score | M1: total_min_score_company_name | N1: Total_max_score | O1: total_max_score_company_name | P1: total_median_score | Q1: total_score_difference | R1: Column 3 | S1: Column 4 | T1: Column 5 | U1: Column 6 | V1: Column 7 | W1: Column 8 | X1: Column 9 | Y1: Column 10 | Z1: Column 11 | AA1: Column 12 | AB1: Column 13 | AC1: Column 14 | AD1: Column 15 | AE1: Column 16 | AF1: Column 17 | AG1: Column 18 | AH1: Column 19 | AI1: Column 20 | AJ1: Column 21 | AK1: Column 22 | AL1: Column 23 | AM1: Column 24 | AN1: Column 25 | AO1: Column 26 | AP1: Column 27 | AQ1: Column 28 | AR1: Column 29 | AS1: Column 30 | AT1: Column 31 | AU1: Column 32 | AV1: Column 33 | AW1: Column 34 | AX1: Column 35 | AY1: Column 36 | AZ1: Column 37 | BA1: Column 38 | BB1: Column 39 | BC1: Column 40 | BD1: Column 41 | BE1: Column 42 | BF1: Column 43 | BG1: Column 44 | BH1: Column 45 | BI1: Column 46
A2: =COUNTIF('Cleaned data'!E:E, B2) -> 63 | B2: Technology | C2: =IFERROR(__xludf.DUMMYFUNCTION("MIN(FILTER('Cleaned data'!L:L, 'Cleaned data'!E:E=B2))"),200.0) -> 200 | D2: =IFERROR(__xludf.DUMMYFUNCTION("MAX(FILTER('Cleaned data'!L:L, 'Cleaned data'!E:E=B2))"),715.0) -> 715 | E2: =IFERROR(__xludf.DUMMYFUNCTION("MEDIAN(FILTER('Cleaned data'!L:L, 'Cleaned data'!E:E=B2))"),500.0) -> 500 | F2: =IFERROR(__xludf.DUMMYFUNCTION("MIN(FILTER('Cleaned data'!M:M, 'Cleaned data'!E:E=B2))"),205.0) -> 205 | G2: =IFERROR(__xludf.DUMMYFUNCTION("MAX(FILTER('Cleaned data'!M:M, 'Cleaned data'!E:E=B2))"),443.0) -> 443 | H2: =IFERROR(__xludf.DUMMYFUNCTION("MEDIAN(FILTER('Cleaned data'!M:M, 'Cleaned data'!E:E=B2))"),307.0) -> 307 | I2: =IFERROR(__xludf.DUMMYFUNCTION("MIN(FILTER('Cleaned data'!N:N,'Cleaned data'!E:E=B2))"),200.0) -> 200 | J2: =IFERROR(__xludf.DUMMYFUNCTION("MAX(FILTER('Cleaned data'!N:N,'Cleaned data'!E:E=B2))"),375.0) -> 375 | K2: =IFERROR(__xludf.DUMMYFUNCTION("MEDIAN(FILTER('Cleaned data'!N:N, 'Cleaned data'!E:E=B2))"),305.0) -> 305 | L2: =IFERROR(__xludf.DUMMYFUNCTION("MIN(FILTER('Cleaned data'!O:O, 'Cleaned data'!E:E=B2))"),621.0) -> 621 | M2: =IFERROR(__xludf.DUMMYFUNCTION("INDEX(FILTER('Cleaned data'!B:B, ('Cleaned data'!E:E=B2)*'Cleaned data'!O:O=MIN(FILTER('Cleaned data'!O:O, 'Cleaned data'!E:E=B2))))"),"Adobe Inc") -> Adobe Inc | N2: =IFERROR(__xludf.DUMMYFUNCTION("MAX(FILTER('Cleaned data'!O:O, 'Cleaned data'!E:E=B2))"),1533.0) -> 1533 | O2: =IFERROR(__xludf.DUMMYFUNCTION("INDEX(FILTER('Cleaned data'!B:B, ('Cleaned data'!E:E=B2)*'Cleaned data'!O:O=MAX(FILTER('Cleaned data'!O:O, 'Cleaned data'!E:E=B2))))"),"Microsoft Corp") -> Microsoft Corp | P2: =IFERROR(__xludf.DUMMYFUNCTION("MEDIAN(FILTER('Cleaned data'!O:O, 'Cleaned data'!E:E=B2))"),1103.0) -> 1103 | Q2: =N2-L2 -> 912
A3: =COUNTIF('Cleaned data'!E:E, B3) -> 56 | B3: Biotechnology | C3: =IFERROR(__xludf.DUMMYFUNCTION("MIN(FILTER('Cleaned data'!L:L, 'Cleaned data'!E:E=B3))"),200.0) -> 200 | D3: =IFERROR(__xludf.DUMMYFUNCTION("MAX(FILTER('Cleaned data'!L:L, 'Cleaned data'!E:E=B3))"),575.0) -> 575 | E3: =IFERROR(__xludf.DUMMYFUNCTION("MEDIAN(FILTER('Cleaned data'!L:L, 'Cleaned data'!E:E=B3))"),240.0) -> 240 | F3: =IFERROR(__xludf.DUMMYFUNCTION("MIN(FILTER('Cleaned data'!M:M, 'Cleaned data'!E:E=B3))"),201.0) -> 201 | G3: =IFERROR(__xludf.DUMMYFUNCTION("MAX(FILTER('Cleaned data'!M:M, 'Cleaned data'!E:E=B3))"),346.0) -> 346 | H3: =IFERROR(__xludf.DUMMYFUNCTION("MEDIAN(FILTER('Cleaned data'!M:M, 'Cleaned data'!E:E=B3))"),280.0) -> 280 | I3: =IFERROR(__xludf.DUMMYFUNCTION("MIN(FILTER('Cleaned data'!N:N,'Cleaned data'!E:E=B3))"),200.0) -> 200 | J3: =IFERROR(__xludf.DUMMYFUNCTION("MAX(FILTER('Cleaned data'!N:N,'Cleaned data'!E:E=B3))"),364.0) -> 364 | K3: =IFERROR(__xludf.DUMMYFUNCTION("MEDIAN(FILTER('Cleaned data'!N:N, 'Cleaned data'!E:E=B3))"),305.0) -> 305 | L3: =IFERROR(__xludf.DUMMYFUNCTION("MIN(FILTER('Cleaned data'!O:O, 'Cleaned data'!E:E=B3))"),604.0) -> 604 | M3: =IFERROR(__xludf.DUMMYFUNCTION("INDEX(FILTER('Cleaned data'!B:B, ('Cleaned data'!E:E=B3)*'Cleaned data'!O:O=MIN(FILTER('Cleaned data'!O:O, 'Cleaned data'!E:E=B3))))"),"Aadi Bioscience Inc") -> Aadi Bioscience Inc | N3: =IFERROR(__xludf.DUMMYFUNCTION("MAX(FILTER('Cleaned data'!O:O, 'Cleaned data'!E:E=B3))"),1215.0) -> 1215 | O3: =IFERROR(__xludf.DUMMYFUNCTION("INDEX(FILTER('Cleaned data'!B:B, ('Cleaned data'!E:E=B3)*'Cleaned data'!O:O=MAX(FILTER('Cleaned data'!O:O, 'Cleaned data'!E:E=B3))))"),"Amgen Inc") -> Amgen Inc | P3: =IFERROR(__xludf.DUMMYFUNCTION("MEDIAN(FILTER('Cleaned data'!O:O, 'Cleaned data'!E:E=B3))"),822.5) -> 822.5 | Q3: =N3-L3 -> 611
A4: =COUNTIF('Cleaned data'!E:E, B4) -> 52 | B4: Health Care | C4: =IFERROR(__xludf.DUMMYFUNCTION("MIN(FILTER('Cleaned data'!L:L, 'Cleaned data'!E:E=B4))"),200.0) -> 200 | D4: =IFERROR(__xludf.DUMMYFUNCTION("MAX(FILTER('Cleaned data'!L:L, 'Cleaned data'!E:E=B4))"),607.0) -> 607 | E4: =IFERROR(__xludf.DUMMYFUNCTION("MEDIAN(FILTER('Cleaned data'!L:L, 'Cleaned data'!E:E=B4))"),385.5) -> 385.5 | F4: =IFERROR(__xludf.DUMMYFUNCTION("MIN(FILTER('Cleaned data'!M:M, 'Cleaned data'!E:E=B4))"),200.0) -> 200 | G4: =IFERROR(__xludf.DUMMYFUNCTION("MAX(FILTER('Cleaned data'!M:M, 'Cleaned data'!E:E=B4))"),399.0) -> 399 | H4: =IFERROR(__xludf.DUMMYFUNCTION("MEDIAN(FILTER('Cleaned data'!M:M, 'Cleaned data'!E:E=B4))"),300.5) -> 300.5 | I4: =IFERROR(__xludf.DUMMYFUNCTION("MIN(FILTER('Cleaned data'!N:N,'Cleaned data'!E:E=B4))"),200.0) -> 200 | J4: =IFERROR(__xludf.DUMMYFUNCTION("MAX(FILTER('Cleaned data'!N:N,'Cleaned data'!E:E=B4))"),338.0) -> 338 | K4: =IFERROR(__xludf.DUMMYFUNCTION("MEDIAN(FILTER('Cleaned data'!N:N, 'Cleaned data'!E:E=B4))"),300.0) -> 300 | L4: =IFERROR(__xludf.DUMMYFUNCTION("MIN(FILTER('Cleaned data'!O:O, 'Cleaned data'!E:E=B4))"),600.0) -> 600 | M4: =IFERROR(__xludf.DUMMYFUNCTION("INDEX(FILTER('Cleaned data'!B:B, ('Cleaned data'!E:E=B4)*'Cleaned data'!O:O=MIN(FILTER('Cleaned data'!O:O, 'Cleaned data'!E:E=B4))))"),"Teleflex Inc") -> Teleflex Inc | N4: =IFERROR(__xludf.DUMMYFUNCTION("MAX(FILTER('Cleaned data'!O:O, 'Cleaned data'!E:E=B4))"),1306.0) -> 1306 | O4: =IFERROR(__xludf.DUMMYFUNCTION("INDEX(FILTER('Cleaned data'!B:B, ('Cleaned data'!E:E=B4)*'Cleaned data'!O:O=MAX(FILTER('Cleaned data'!O:O, 'Cleaned data'!E:E=B4))))"),"Becton Dickinson and Co") -> Becton Dickinson and Co | P4: =IFERROR(__xludf.DUMMYFUNCTION("MEDIAN(FILTER('Cleaned data'!O:O, 'Cleaned data'!E:E=B4))"),976.5) -> 976.5 | Q4: =N4-L4 -> 706
A5: =COUNTIF('Cleaned data'!E:E, B5) -> 36 | B5: Real Estate | C5: =IFERROR(__xludf.DUMMYFUNCTION("MIN(FILTER('Cleaned data'!L:L, 'Cleaned data'!E:E=B5))"),200.0) -> 200 | D5: =IFERROR(__xludf.DUMMYFUNCTION("MAX(FILTER('Cleaned data'!L:L, 'Cleaned data'!E:E=B5))"),700.0) -> 700 | E5: =IFERROR(__xludf.DUMMYFUNCTION("MEDIAN(FILTER('Cleaned data'!L:L, 'Cleaned data'!E:E=B5))"),500.0) -> 500 | F5: =IFERROR(__xludf.DUMMYFUNCTION("MIN(FILTER('Cleaned data'!M:M, 'Cleaned data'!E:E=B5))"),204.0) -> 204 | G5: =IFERROR(__xludf.DUMMYFUNCTION("MAX(FILTER('Cleaned data'!M:M, 'Cleaned data'!E:E=B5))"),404.0) -> 404 | H5: =IFERROR(__xludf.DUMMYFUNCTION("MEDIAN(FILTER('Cleaned data'!M:M, 'Cleaned data'!E:E=B5))"),300.0) -> 300 | I5: =IFERROR(__xludf.DUMMYFUNCTION("MIN(FILTER('Cleaned data'!N:N,'Cleaned data'!E:E=B5))"),200.0) -> 200 | J5: =IFERROR(__xludf.DUMMYFUNCTION("MAX(FILTER('Cleaned data'!N:N,'Cleaned data'!E:E=B5))"),365.0) -> 365 | K5: =IFERROR(__xludf.DUMMYFUNCTION("MEDIAN(FILTER('Cleaned data'!N:N, 'Cleaned data'!E:E=B5))"),300.0) -> 300 | L5: =IFERROR(__xludf.DUMMYFUNCTION("MIN(FILTER('Cleaned data'!O:O, 'Cleaned data'!E:E=B5))"),609.0) -> 609 | M5: =IFERROR(__xludf.DUMMYFUNCTION("INDEX(FILTER('Cleaned data'!B:B, ('Cleaned data'!E:E=B5)*'Cleaned data'!O:O=MIN(FILTER('Cleaned data'!O:O, 'Cleaned data'!E:E=B5))))"),"CBRE Group Inc") -> CBRE Group Inc | N5: =IFERROR(__xludf.DUMMYFUNCTION("MAX(FILTER('Cleaned data'!O:O, 'Cleaned data'!E:E=B5))"),1363.0) -> 1363 | O5: =IFERROR(__xludf.DUMMYFUNCTION("INDEX(FILTER('Cleaned data'!B:B, ('Cleaned data'!E:E=B5)*'Cleaned data'!O:O=MAX(FILTER('Cleaned data'!O:O, 'Cleaned data'!E:E=B5))))"),"Hannon Armstrong Sustainable Infrastructure Capital Inc") -> Hannon Armstrong Sustainable Infrastructure Capital Inc | P5: =IFERROR(__xludf.DUMMYFUNCTION("MEDIAN(FILTER('Cleaned data'!O:O, 'Cleaned data'!E:E=B5))"),1092.0) -> 1092 | Q5: =N5-L5 -> 754
A6: =COUNTIF('Cleaned data'!E:E, B6) -> 33 | B6: Financial Services | C6: =IFERROR(__xludf.DUMMYFUNCTION("MIN(FILTER('Cleaned data'!L:L, 'Cleaned data'!E:E=B6))"),200.0) -> 200 | D6: =IFERROR(__xludf.DUMMYFUNCTION("MAX(FILTER('Cleaned data'!L:L, 'Cleaned data'!E:E=B6))"),580.0) -> 580 | E6: =IFERROR(__xludf.DUMMYFUNCTION("MEDIAN(FILTER('Cleaned data'!L:L, 'Cleaned data'!E:E=B6))"),335.0) -> 335 | F6: =IFERROR(__xludf.DUMMYFUNCTION("MIN(FILTER('Cleaned data'!M:M, 'Cleaned data'!E:E=B6))"),200.0) -> 200 | G6: =IFERROR(__xludf.DUMMYFUNCTION("MAX(FILTER('Cleaned data'!M:M, 'Cleaned data'!E:E=B6))"),350.0) -> 350 | H6: =IFERROR(__xludf.DUMMYFUNCTION("MEDIAN(FILTER('Cleaned data'!M:M, 'Cleaned data'!E:E=B6))"),303.0) -> 303 | I6: =IFERROR(__xludf.DUMMYFUNCTION("MIN(FILTER('Cleaned data'!N:N,'Cleaned data'!E:E=B6))"),200.0) -> 200 | J6: =IFERROR(__xludf.DUMMYFUNCTION("MAX(FILTER('Cleaned data'!N:N,'Cleaned data'!E:E=B6))"),335.0) -> 335 | K6: =IFERROR(__xludf.DUMMYFUNCTION("MEDIAN(FILTER('Cleaned data'!N:N, 'Cleaned data'!E:E=B6))"),275.0) -> 275 | L6: =IFERROR(__xludf.DUMMYFUNCTION("MIN(FILTER('Cleaned data'!O:O, 'Cleaned data'!E:E=B6))"),610.0) -> 610 | M6: =IFERROR(__xludf.DUMMYFUNCTION("INDEX(FILTER('Cleaned data'!B:B, ('Cleaned data'!E:E=B6)*'Cleaned data'!O:O=MIN(FILTER('Cleaned data'!O:O, 'Cleaned data'!E:E=B6))))"),"Yiren Digital Ltd") -> Yiren Digital Ltd | N6: =IFERROR(__xludf.DUMMYFUNCTION("MAX(FILTER('Cleaned data'!O:O, 'Cleaned data'!E:E=B6))"),1262.0) -> 1262 | O6: =IFERROR(__xludf.DUMMYFUNCTION("INDEX(FILTER('Cleaned data'!B:B, ('Cleaned data'!E:E=B6)*'Cleaned data'!O:O=MAX(FILTER('Cleaned data'!O:O, 'Cleaned data'!E:E=B6))))"),"MSCI Inc") -> MSCI Inc | P6: =IFERROR(__xludf.DUMMYFUNCTION("MEDIAN(FILTER('Cleaned data'!O:O, 'Cleaned data'!E:E=B6))"),969.0) -> 969 | Q6: =N6-L6 -> 652
A7: =COUNTIF('Cleaned data'!E:E, B7) -> 30 | B7: Utilities | C7: =IFERROR(__xludf.DUMMYFUNCTION("MIN(FILTER('Cleaned data'!L:L, 'Cleaned data'!E:E=B7))"),223.0) -> 223 | D7: =IFERROR(__xludf.DUMMYFUNCTION("MAX(FILTER('Cleaned data'!L:L, 'Cleaned data'!E:E=B7))"),700.0) -> 700 | E7: =IFERROR(__xludf.DUMMYFUNCTION("MEDIAN(FILTER('Cleaned data'!L:L, 'Cleaned data'!E:E=B7))"),558.5) -> 558.5 | F7: =IFERROR(__xludf.DUMMYFUNCTION("MIN(FILTER('Cleaned data'!M:M, 'Cleaned data'!E:E=B7))"),201.0) -> 201 | G7: =IFERROR(__xludf.DUMMYFUNCTION("MAX(FILTER('Cleaned data'!M:M, 'Cleaned data'!E:E=B7))"),667.0) -> 667 | H7: =IFERROR(__xludf.DUMMYFUNCTION("MEDIAN(FILTER('Cleaned data'!M:M, 'Cleaned data'!E:E=B7))"),326.5) -> 326.5 | I7: =IFERROR(__xludf.DUMMYFUNCTION("MIN(FILTER('Cleaned data'!N:N,'Cleaned data'!E:E=B7))"),75.0) -> 75 | J7: =IFERROR(__xludf.DUMMYFUNCTION("MAX(FILTER('Cleaned data'!N:N,'Cleaned data'!E:E=B7))"),370.0) -> 370 | K7: =IFERROR(__xludf.DUMMYFUNCTION("MEDIAN(FILTER('Cleaned data'!N:N, 'Cleaned data'!E:E=B7))"),300.0) -> 300 | L7: =IFERROR(__xludf.DUMMYFUNCTION("MIN(FILTER('Cleaned data'!O:O, 'Cleaned data'!E:E=B7))"),629.0) -> 629 | M7: =IFERROR(__xludf.DUMMYFUNCTION("INDEX(FILTER('Cleaned data'!B:B, ('Cleaned data'!E:E=B7)*'Cleaned data'!O:O=MIN(FILTER('Cleaned data'!O:O, 'Cleaned data'!E:E=B7))))"),"Xcel Energy Inc") -> Xcel Energy Inc | N7: =IFERROR(__xludf.DUMMYFUNCTION("MAX(FILTER('Cleaned data'!O:O, 'Cleaned data'!E:E=B7))"),1528.0) -> 1528 | O7: =IFERROR(__xludf.DUMMYFUNCTION("INDEX(FILTER('Cleaned data'!B:B, ('Cleaned data'!E:E=B7)*'Cleaned data'!O:O=MAX(FILTER('Cleaned data'!O:O, 'Cleaned data'!E:E=B7))))"),"Edison International") -> Edison International | P7: =IFERROR(__xludf.DUMMYFUNCTION("MEDIAN(FILTER('Cleaned data'!O:O, 'Cleaned data'!E:E=B7))"),1199.5) -> 1199.5 | Q7: =N7-L7 -> 899
A8: =COUNTIF('Cleaned data'!E:E, B8) -> 29 | B8: Banking | C8: =IFERROR(__xludf.DUMMYFUNCTION("MIN(FILTER('Cleaned data'!L:L, 'Cleaned data'!E:E=B8))"),200.0) -> 200 | D8: =IFERROR(__xludf.DUMMYFUNCTION("MAX(FILTER('Cleaned data'!L:L, 'Cleaned data'!E:E=B8))"),565.0) -> 565 | E8: =IFERROR(__xludf.DUMMYFUNCTION("MEDIAN(FILTER('Cleaned data'!L:L, 'Cleaned data'!E:E=B8))"),308.0) -> 308 | F8: =IFERROR(__xludf.DUMMYFUNCTION("MIN(FILTER('Cleaned data'!M:M, 'Cleaned data'!E:E=B8))"),200.0) -> 200 | G8: =IFERROR(__xludf.DUMMYFUNCTION("MAX(FILTER('Cleaned data'!M:M, 'Cleaned data'!E:E=B8))"),394.0) -> 394 | H8: =IFERROR(__xludf.DUMMYFUNCTION("MEDIAN(FILTER('Cleaned data'!M:M, 'Cleaned data'!E:E=B8))"),300.0) -> 300 | I8: =IFERROR(__xludf.DUMMYFUNCTION("MIN(FILTER('Cleaned data'!N:N,'Cleaned data'!E:E=B8))"),200.0) -> 200 | J8: =IFERROR(__xludf.DUMMYFUNCTION("MAX(FILTER('Cleaned data'!N:N,'Cleaned data'!E:E=B8))"),338.0) -> 338 | K8: =IFERROR(__xludf.DUMMYFUNCTION("MEDIAN(FILTER('Cleaned data'!N:N, 'Cleaned data'!E:E=B8))"),265.0) -> 265 | L8: =IFERROR(__xludf.DUMMYFUNCTION("MIN(FILTER('Cleaned data'!O:O, 'Cleaned data'!E:E=B8))"),600.0) -> 600 | M8: =IFERROR(__xludf.DUMMYFUNCTION("INDEX(FILTER('Cleaned data'!B:B, ('Cleaned data'!E:E=B8)*'Cleaned data'!O:O=MIN(FILTER('Cleaned data'!O:O, 'Cleaned data'!E:E=B8))))"),"Zions Bancorporation NA") -> Zions Bancorporation NA | N8: =IFERROR(__xludf.DUMMYFUNCTION("MAX(FILTER('Cleaned data'!O:O, 'Cleaned data'!E:E=B8))"),1208.0) -> 1208 | O8: =IFERROR(__xludf.DUMMYFUNCTION("INDEX(FILTER('Cleaned data'!B:B, ('Cleaned data'!E:E=B8)*'Cleaned data'!O:O=MAX(FILTER('Cleaned data'!O:O, 'Cleaned data'!E:E=B8))))"),"Pacific Premier Bancorp Inc") -> Pacific Premier Bancorp Inc | P8: =IFERROR(__xludf.DUMMYFUNCTION("MEDIAN(FILTER('Cleaned data'!O:O, 'Cleaned data'!E:E=B8))"),886.0) -> 886 | Q8: =N8-L8 -> 608
A9: =COUNTIF('Cleaned data'!E:E, B9) -> 27 | B9: Electrical Equipment | C9: =IFERROR(__xludf.DUMMYFUNCTION("MIN(FILTER('Cleaned data'!L:L, 'Cleaned data'!E:E=B9))"),200.0) -> 200 | D9: =IFERROR(__xludf.DUMMYFUNCTION("MAX(FILTER('Cleaned data'!L:L, 'Cleaned data'!E:E=B9))"),605.0) -> 605 | E9: =IFERROR(__xludf.DUMMYFUNCTION("MEDIAN(FILTER('Cleaned data'!L:L, 'Cleaned data'!E:E=B9))"),410.0) -> 410 | F9: =IFERROR(__xludf.DUMMYFUNCTION("MIN(FILTER('Cleaned data'!M:M, 'Cleaned data'!E:E=B9))"),200.0) -> 200 | G9: =IFERROR(__xludf.DUMMYFUNCTION("MAX(FILTER('Cleaned data'!M:M, 'Cleaned data'!E:E=B9))"),415.0) -> 415 | H9: =IFERROR(__xludf.DUMMYFUNCTION("MEDIAN(FILTER('Cleaned data'!M:M, 'Cleaned data'!E:E=B9))"),300.0) -> 300 | I9: =IFERROR(__xludf.DUMMYFUNCTION("MIN(FILTER('Cleaned data'!N:N,'Cleaned data'!E:E=B9))"),200.0) -> 200 | J9: =IFERROR(__xludf.DUMMYFUNCTION("MAX(FILTER('Cleaned data'!N:N,'Cleaned data'!E:E=B9))"),475.0) -> 475 | K9: =IFERROR(__xludf.DUMMYFUNCTION("MEDIAN(FILTER('Cleaned data'!N:N, 'Cleaned data'!E:E=B9))"),300.0) -> 300 | L9: =IFERROR(__xludf.DUMMYFUNCTION("MIN(FILTER('Cleaned data'!O:O, 'Cleaned data'!E:E=B9))"),600.0) -> 600 | M9: =IFERROR(__xludf.DUMMYFUNCTION("INDEX(FILTER('Cleaned data'!B:B, ('Cleaned data'!E:E=B9)*'Cleaned data'!O:O=MIN(FILTER('Cleaned data'!O:O, 'Cleaned data'!E:E=B9))),1)"),"Corning Inc") -> Corning Inc | N9: =IFERROR(__xludf.DUMMYFUNCTION("MAX(FILTER('Cleaned data'!O:O, 'Cleaned data'!E:E=B9))"),1290.0) -> 1290 | O9: =IFERROR(__xludf.DUMMYFUNCTION("INDEX(FILTER('Cleaned data'!B:B, ('Cleaned data'!E:E=B9)*'Cleaned data'!O:O=MAX(FILTER('Cleaned data'!O:O, 'Cleaned data'!E:E=B9))))"),"Amphenol Corp") -> Amphenol Corp | P9: =IFERROR(__xludf.DUMMYFUNCTION("MEDIAN(FILTER('Cleaned data'!O:O, 'Cleaned data'!E:E=B9))"),937.0) -> 937 | Q9: =N9-L9 -> 690
A10: =COUNTIF('Cleaned data'!E:E, B10) -> 27 | B10: Insurance | C10: =IFERROR(__xludf.DUMMYFUNCTION("MIN(FILTER('Cleaned data'!L:L, 'Cleaned data'!E:E=B10))"),205.0) -> 205 | D10: =IFERROR(__xludf.DUMMYFUNCTION("MAX(FILTER('Cleaned data'!L:L, 'Cleaned data'!E:E=B10))"),700.0) -> 700 | E10: =IFERROR(__xludf.DUMMYFUNCTION("MEDIAN(FILTER('Cleaned data'!L:L, 'Cleaned data'!E:E=B10))"),500.0) -> 500 | F10: =IFERROR(__xludf.DUMMYFUNCTION("MIN(FILTER('Cleaned data'!M:M, 'Cleaned data'!E:E=B10))"),221.0) -> 221 | G10: =IFERROR(__xludf.DUMMYFUNCTION("MAX(FILTER('Cleaned data'!M:M, 'Cleaned data'!E:E=B10))"),355.0) -> 355 | H10: =IFERROR(__xludf.DUMMYFUNCTION("MEDIAN(FILTER('Cleaned data'!M:M, 'Cleaned data'!E:E=B10))"),300.0) -> 300 | I10: =IFERROR(__xludf.DUMMYFUNCTION("MIN(FILTER('Cleaned data'!N:N,'Cleaned data'!E:E=B10))"),215.0) -> 215 | J10: =IFERROR(__xludf.DUMMYFUNCTION("MAX(FILTER('Cleaned data'!N:N,'Cleaned data'!E:E=B10))"),340.0) -> 340 | K10: =IFERROR(__xludf.DUMMYFUNCTION("MEDIAN(FILTER('Cleaned data'!N:N, 'Cleaned data'!E:E=B10))"),300.0) -> 300 | L10: =IFERROR(__xludf.DUMMYFUNCTION("MIN(FILTER('Cleaned data'!O:O, 'Cleaned data'!E:E=B10))"),668.0) -> 668 | M10: =IFERROR(__xludf.DUMMYFUNCTION("INDEX(FILTER('Cleaned data'!B:B, ('Cleaned data'!E:E=B10)*'Cleaned data'!O:O=MIN(FILTER('Cleaned data'!O:O, 'Cleaned data'!E:E=B10))))"),"Globe Life Inc") -> Globe Life Inc | N10: =IFERROR(__xludf.DUMMYFUNCTION("MAX(FILTER('Cleaned data'!O:O, 'Cleaned data'!E:E=B10))"),1300.0) -> 1300 | O10: =IFERROR(__xludf.DUMMYFUNCTION("INDEX(FILTER('Cleaned data'!B:B, ('Cleaned data'!E:E=B10)*'Cleaned data'!O:O=MAX(FILTER('Cleaned data'!O:O, 'Cleaned data'!E:E=B10))))"),"Lincoln National Corp") -> Lincoln National Corp | P10: =IFERROR(__xludf.DUMMYFUNCTION("MEDIAN(FILTER('Cleaned data'!O:O, 'Cleaned data'!E:E=B10))"),1077.0) -> 1077 | Q10: =N10-L10 -> 632
A11: =COUNTIF('Cleaned data'!E:E, B11) -> 26 | B11: Retail | C11: =IFERROR(__xludf.DUMMYFUNCTION("MIN(FILTER('Cleaned data'!L:L, 'Cleaned data'!E:E=B11))"),203.0) -> 203 | D11: =IFERROR(__xludf.DUMMYFUNCTION("MAX(FILTER('Cleaned data'!L:L, 'Cleaned data'!E:E=B11))"),668.0) -> 668 | E11: =IFERROR(__xludf.DUMMYFUNCTION("MEDIAN(FILTER('Cleaned data'!L:L, 'Cleaned data'!E:E=B11))"),355.0) -> 355 | F11: =IFERROR(__xludf.DUMMYFUNCTION("MIN(FILTER('Cleaned data'!M:M, 'Cleaned data'!E:E=B11))"),200.0) -> 200 | G11: =IFERROR(__xludf.DUMMYFUNCTION("MAX(FILTER('Cleaned data'!M:M, 'Cleaned data'!E:E=B11))"),349.0) -> 349 | H11: =IFERROR(__xludf.DUMMYFUNCTION("MEDIAN(FILTER('Cleaned data'!M:M, 'Cleaned data'!E:E=B11))"),300.0) -> 300 | I11: =IFERROR(__xludf.DUMMYFUNCTION("MIN(FILTER('Cleaned data'!N:N,'Cleaned data'!E:E=B11))"),200.0) -> 200 | J11: =IFERROR(__xludf.DUMMYFUNCTION("MAX(FILTER('Cleaned data'!N:N,'Cleaned data'!E:E=B11))"),460.0) -> 460 | K11: =IFERROR(__xludf.DUMMYFUNCTION("MEDIAN(FILTER('Cleaned data'!N:N, 'Cleaned data'!E:E=B11))"),267.5) -> 267.5 | L11: =IFERROR(__xludf.DUMMYFUNCTION("MIN(FILTER('Cleaned data'!O:O, 'Cleaned data'!E:E=B11))"),618.0) -> 618 | M11: =IFERROR(__xludf.DUMMYFUNCTION("INDEX(FILTER('Cleaned data'!B:B, ('Cleaned data'!E:E=B11)*'Cleaned data'!O:O=MIN(FILTER('Cleaned data'!O:O, 'Cleaned data'!E:E=B11))))"),"Lowe's Companies Inc") -> Lowe's Companies Inc | N11: =IFERROR(__xludf.DUMMYFUNCTION("MAX(FILTER('Cleaned data'!O:O, 'Cleaned data'!E:E=B11))"),1433.0) -> 1433 | O11: =IFERROR(__xludf.DUMMYFUNCTION("INDEX(FILTER('Cleaned data'!B:B, ('Cleaned data'!E:E=B11)*'Cleaned data'!O:O=MAX(FILTER('Cleaned data'!O:O, 'Cleaned data'!E:E=B11))))"),"Amazon.com Inc") -> Amazon.com Inc | P11: =IFERROR(__xludf.DUMMYFUNCTION("MEDIAN(FILTER('Cleaned data'!O:O, 'Cleaned data'!E:E=B11))"),948.0) -> 948 | Q11: =N11-L11 -> 815
A12: =COUNTIF('Cleaned data'!E:E, B12) -> 24 | B12: Hotels Restaurants and Leisure | C12: =IFERROR(__xludf.DUMMYFUNCTION("MIN(FILTER('Cleaned data'!L:L, 'Cleaned data'!E:E=B12))"),200.0) -> 200 | D12: =IFERROR(__xludf.DUMMYFUNCTION("MAX(FILTER('Cleaned data'!L:L, 'Cleaned data'!E:E=B12))"),558.0) -> 558 | E12: =IFERROR(__xludf.DUMMYFUNCTION("MEDIAN(FILTER('Cleaned data'!L:L, 'Cleaned data'!E:E=B12))"),338.0) -> 338 | F12: =IFERROR(__xludf.DUMMYFUNCTION("MIN(FILTER('Cleaned data'!M:M, 'Cleaned data'!E:E=B12))"),200.0) -> 200 | G12: =IFERROR(__xludf.DUMMYFUNCTION("MAX(FILTER('Cleaned data'!M:M, 'Cleaned data'!E:E=B12))"),570.0) -> 570 | H12: =IFERROR(__xludf.DUMMYFUNCTION("MEDIAN(FILTER('Cleaned data'!M:M, 'Cleaned data'!E:E=B12))"),294.0) -> 294 | I12: =IFERROR(__xludf.DUMMYFUNCTION("MIN(FILTER('Cleaned data'!N:N,'Cleaned data'!E:E=B12))"),200.0) -> 200 | J12: =IFERROR(__xludf.DUMMYFUNCTION("MAX(FILTER('Cleaned data'!N:N,'Cleaned data'!E:E=B12))"),400.0) -> 400 | K12: =IFERROR(__xludf.DUMMYFUNCTION("MEDIAN(FILTER('Cleaned data'!N:N, 'Cleaned data'!E:E=B12))"),235.0) -> 235 | L12: =IFERROR(__xludf.DUMMYFUNCTION("MIN(FILTER('Cleaned data'!O:O, 'Cleaned data'!E:E=B12))"),600.0) -> 600 | M12: =IFERROR(__xludf.DUMMYFUNCTION("INDEX(FILTER('Cleaned data'!B:B, ('Cleaned data'!E:E=B12)*'Cleaned data'!O:O=MIN(FILTER('Cleaned data'!O:O, 'Cleaned data'!E:E=B12))))"),"Allied Esports Entertainment Inc") -> Allied Esports Entertainment Inc | N12: =IFERROR(__xludf.DUMMYFUNCTION("MAX(FILTER('Cleaned data'!O:O, 'Cleaned data'!E:E=B12))"),1475.0) -> 1475 | O12: =IFERROR(__xludf.DUMMYFUNCTION("INDEX(FILTER('Cleaned data'!B:B, ('Cleaned data'!E:E=B12)*'Cleaned data'!O:O=MAX(FILTER('Cleaned data'!O:O, 'Cleaned data'!E:E=B12))))"),"Airbnb Inc") -> Airbnb Inc | P12: =IFERROR(__xludf.DUMMYFUNCTION("MEDIAN(FILTER('Cleaned data'!O:O, 'Cleaned data'!E:E=B12))"),867.0) -> 867 | Q12: =N12-L12 -> 875
A13: =COUNTIF('Cleaned data'!E:E, B13) -> 24 | B13: Semiconductors | C13: =IFERROR(__xludf.DUMMYFUNCTION("MIN(FILTER('Cleaned data'!L:L, 'Cleaned data'!E:E=B13))"),200.0) -> 200 | D13: =IFERROR(__xludf.DUMMYFUNCTION("MAX(FILTER('Cleaned data'!L:L, 'Cleaned data'!E:E=B13))"),575.0) -> 575 | E13: =IFERROR(__xludf.DUMMYFUNCTION("MEDIAN(FILTER('Cleaned data'!L:L, 'Cleaned data'!E:E=B13))"),505.0) -> 505 | F13: =IFERROR(__xludf.DUMMYFUNCTION("MIN(FILTER('Cleaned data'!M:M, 'Cleaned data'!E:E=B13))"),208.0) -> 208 | G13: =IFERROR(__xludf.DUMMYFUNCTION("MAX(FILTER('Cleaned data'!M:M, 'Cleaned data'!E:E=B13))"),330.0) -> 330 | H13: =IFERROR(__xludf.DUMMYFUNCTION("MEDIAN(FILTER('Cleaned data'!M:M, 'Cleaned data'!E:E=B13))"),305.0) -> 305 | I13: =IFERROR(__xludf.DUMMYFUNCTION("MIN(FILTER('Cleaned data'!N:N,'Cleaned data'!E:E=B13))"),200.0) -> 200 | J13: =IFERROR(__xludf.DUMMYFUNCTION("MAX(FILTER('Cleaned data'!N:N,'Cleaned data'!E:E=B13))"),335.0) -> 335 | K13: =IFERROR(__xludf.DUMMYFUNCTION("MEDIAN(FILTER('Cleaned data'!N:N, 'Cleaned data'!E:E=B13))"),300.0) -> 300 | L13: =IFERROR(__xludf.DUMMYFUNCTION("MIN(FILTER('Cleaned data'!O:O, 'Cleaned data'!E:E=B13))"),608.0) -> 608 | M13: =IFERROR(__xludf.DUMMYFUNCTION("INDEX(FILTER('Cleaned data'!B:B, ('Cleaned data'!E:E=B13)*'Cleaned data'!O:O=MIN(FILTER('Cleaned data'!O:O, 'Cleaned data'!E:E=B13))))"),"Advanced Micro Devices Inc") -> Advanced Micro Devices Inc | N13: =IFERROR(__xludf.DUMMYFUNCTION("MAX(FILTER('Cleaned data'!O:O, 'Cleaned data'!E:E=B13))"),1195.0) -> 1195 | O13: =IFERROR(__xludf.DUMMYFUNCTION("INDEX(FILTER('Cleaned data'!B:B, ('Cleaned data'!E:E=B13)*'Cleaned data'!O:O=MAX(FILTER('Cleaned data'!O:O, 'Cleaned data'!E:E=B13))))"),"Maxlinear Inc") -> Maxlinear Inc | P13: =IFERROR(__xludf.DUMMYFUNCTION("MEDIAN(FILTER('Cleaned data'!O:O, 'Cleaned data'!E:E=B13))"),1100.0) -> 1100 | Q13: =N13-L13 -> 587
A14: =COUNTIF('Cleaned data'!E:E, B14) -> 23 | B14: Media | C14: =IFERROR(__xludf.DUMMYFUNCTION("MIN(FILTER('Cleaned data'!L:L, 'Cleaned data'!E:E=B14))"),205.0) -> 205 | D14: =IFERROR(__xludf.DUMMYFUNCTION("MAX(FILTER('Cleaned data'!L:L, 'Cleaned data'!E:E=B14))"),543.0) -> 543 | E14: =IFERROR(__xludf.DUMMYFUNCTION("MEDIAN(FILTER('Cleaned data'!L:L, 'Cleaned data'!E:E=B14))"),295.0) -> 295 | F14: =IFERROR(__xludf.DUMMYFUNCTION("MIN(FILTER('Cleaned data'!M:M, 'Cleaned data'!E:E=B14))"),202.0) -> 202 | G14: =IFERROR(__xludf.DUMMYFUNCTION("MAX(FILTER('Cleaned data'!M:M, 'Cleaned data'!E:E=B14))"),515.0) -> 515 | H14: =IFERROR(__xludf.DUMMYFUNCTION("MEDIAN(FILTER('Cleaned data'!M:M, 'Cleaned data'!E:E=B14))"),307.0) -> 307 | I14: =IFERROR(__xludf.DUMMYFUNCTION("MIN(FILTER('Cleaned data'!N:N,'Cleaned data'!E:E=B14))"),200.0) -> 200 | J14: =IFERROR(__xludf.DUMMYFUNCTION("MAX(FILTER('Cleaned data'!N:N,'Cleaned data'!E:E=B14))"),355.0) -> 355 | K14: =IFERROR(__xludf.DUMMYFUNCTION("MEDIAN(FILTER('Cleaned data'!N:N, 'Cleaned data'!E:E=B14))"),300.0) -> 300 | L14: =IFERROR(__xludf.DUMMYFUNCTION("MIN(FILTER('Cleaned data'!O:O, 'Cleaned data'!E:E=B14))"),607.0) -> 607 | M14: =IFERROR(__xludf.DUMMYFUNCTION("INDEX(FILTER('Cleaned data'!B:B, ('Cleaned data'!E:E=B14)*'Cleaned data'!O:O=MIN(FILTER('Cleaned data'!O:O, 'Cleaned data'!E:E=B14))))"),"Playstudios Inc") -> Playstudios Inc | N14: =IFERROR(__xludf.DUMMYFUNCTION("MAX(FILTER('Cleaned data'!O:O, 'Cleaned data'!E:E=B14))"),1181.0) -> 1181 | O14: =IFERROR(__xludf.DUMMYFUNCTION("INDEX(FILTER('Cleaned data'!B:B, ('Cleaned data'!E:E=B14)*'Cleaned data'!O:O=MAX(FILTER('Cleaned data'!O:O, 'Cleaned data'!E:E=B14))))"),"Omnicom Group Inc") -> Omnicom Group Inc | P14: =IFERROR(__xludf.DUMMYFUNCTION("MEDIAN(FILTER('Cleaned data'!O:O, 'Cleaned data'!E:E=B14))"),945.0) -> 945 | Q14: =N14-L14 -> 574
A15: =COUNTIF('Cleaned data'!E:E, B15) -> 21 | B15: Energy | C15: =IFERROR(__xludf.DUMMYFUNCTION("MIN(FILTER('Cleaned data'!L:L, 'Cleaned data'!E:E=B15))"),200.0) -> 200 | D15: =IFERROR(__xludf.DUMMYFUNCTION("MAX(FILTER('Cleaned data'!L:L, 'Cleaned data'!E:E=B15))"),700.0) -> 700 | E15: =IFERROR(__xludf.DUMMYFUNCTION("MEDIAN(FILTER('Cleaned data'!L:L, 'Cleaned data'!E:E=B15))"),535.0) -> 535 | F15: =IFERROR(__xludf.DUMMYFUNCTION("MIN(FILTER('Cleaned data'!M:M, 'Cleaned data'!E:E=B15))"),200.0) -> 200 | G15: =IFERROR(__xludf.DUMMYFUNCTION("MAX(FILTER('Cleaned data'!M:M, 'Cleaned data'!E:E=B15))"),544.0) -> 544 | H15: =IFERROR(__xludf.DUMMYFUNCTION("MEDIAN(FILTER('Cleaned data'!M:M, 'Cleaned data'!E:E=B15))"),302.0) -> 302 | I15: =IFERROR(__xludf.DUMMYFUNCTION("MIN(FILTER('Cleaned data'!N:N,'Cleaned data'!E:E=B15))"),210.0) -> 210 | J15: =IFERROR(__xludf.DUMMYFUNCTION("MAX(FILTER('Cleaned data'!N:N,'Cleaned data'!E:E=B15))"),355.0) -> 355 | K15: =IFERROR(__xludf.DUMMYFUNCTION("MEDIAN(FILTER('Cleaned data'!N:N, 'Cleaned data'!E:E=B15))"),305.0) -> 305 | L15: =IFERROR(__xludf.DUMMYFUNCTION("MIN(FILTER('Cleaned data'!O:O, 'Cleaned data'!E:E=B15))"),637.0) -> 637 | M15: =IFERROR(__xludf.DUMMYFUNCTION("INDEX(FILTER('Cleaned data'!B:B, ('Cleaned data'!E:E=B15)*'Cleaned data'!O:O=MIN(FILTER('Cleaned data'!O:O, 'Cleaned data'!E:E=B15))))"),"Chevron Corp") -> Chevron Corp | N15: =IFERROR(__xludf.DUMMYFUNCTION("MAX(FILTER('Cleaned data'!O:O, 'Cleaned data'!E:E=B15))"),1536.0) -> 1536 | O15: =IFERROR(__xludf.DUMMYFUNCTION("INDEX(FILTER('Cleaned data'!B:B, ('Cleaned data'!E:E=B15)*'Cleaned data'!O:O=MAX(FILTER('Cleaned data'!O:O, 'Cleaned data'!E:E=B15))))"),"Conocophillips") -> Conocophillips | P15: =IFERROR(__xludf.DUMMYFUNCTION("MEDIAN(FILTER('Cleaned data'!O:O, 'Cleaned data'!E:E=B15))"),1148.0) -> 1148 | Q15: =N15-L15 -> 899
A16: =COUNTIF('Cleaned data'!E:E, B16) -> 21 | B16: Pharmaceuticals | C16: =IFERROR(__xludf.DUMMYFUNCTION("MIN(FILTER('Cleaned data'!L:L, 'Cleaned data'!E:E=B16))"),200.0) -> 200 | D16: =IFERROR(__xludf.DUMMYFUNCTION("MAX(FILTER('Cleaned data'!L:L, 'Cleaned data'!E:E=B16))"),565.0) -> 565 | E16: =IFERROR(__xludf.DUMMYFUNCTION("MEDIAN(FILTER('Cleaned data'!L:L, 'Cleaned data'!E:E=B16))"),285.0) -> 285 | F16: =IFERROR(__xludf.DUMMYFUNCTION("MIN(FILTER('Cleaned data'!M:M, 'Cleaned data'!E:E=B16))"),203.0) -> 203 | G16: =IFERROR(__xludf.DUMMYFUNCTION("MAX(FILTER('Cleaned data'!M:M, 'Cleaned data'!E:E=B16))"),360.0) -> 360 | H16: =IFERROR(__xludf.DUMMYFUNCTION("MEDIAN(FILTER('Cleaned data'!M:M, 'Cleaned data'!E:E=B16))"),264.0) -> 264 | I16: =IFERROR(__xludf.DUMMYFUNCTION("MIN(FILTER('Cleaned data'!N:N,'Cleaned data'!E:E=B16))"),200.0) -> 200 | J16: =IFERROR(__xludf.DUMMYFUNCTION("MAX(FILTER('Cleaned data'!N:N,'Cleaned data'!E:E=B16))"),315.0) -> 315 | K16: =IFERROR(__xludf.DUMMYFUNCTION("MEDIAN(FILTER('Cleaned data'!N:N, 'Cleaned data'!E:E=B16))"),300.0) -> 300 | L16: =IFERROR(__xludf.DUMMYFUNCTION("MIN(FILTER('Cleaned data'!O:O, 'Cleaned data'!E:E=B16))"),645.0) -> 645 | M16: =IFERROR(__xludf.DUMMYFUNCTION("INDEX(FILTER('Cleaned data'!B:B, ('Cleaned data'!E:E=B16)*'Cleaned data'!O:O=MIN(FILTER('Cleaned data'!O:O, 'Cleaned data'!E:E=B16))))"),"Clearside Biomedical Inc") -> Clearside Biomedical Inc | N16: =IFERROR(__xludf.DUMMYFUNCTION("MAX(FILTER('Cleaned data'!O:O, 'Cleaned data'!E:E=B16))"),1180.0) -> 1180 | O16: =IFERROR(__xludf.DUMMYFUNCTION("INDEX(FILTER('Cleaned data'!B:B, ('Cleaned data'!E:E=B16)*'Cleaned data'!O:O=MAX(FILTER('Cleaned data'!O:O, 'Cleaned data'!E:E=B16))))"),"Eli Lilly and Co") -> Eli Lilly and Co | P16: =IFERROR(__xludf.DUMMYFUNCTION("MEDIAN(FILTER('Cleaned data'!O:O, 'Cleaned data'!E:E=B16))"),824.0) -> 824 | Q16: =N16-L16 -> 535
A17: =COUNTIF('Cleaned data'!E:E, B17) -> 21 | B17: Machinery | C17: =IFERROR(__xludf.DUMMYFUNCTION("MIN(FILTER('Cleaned data'!L:L, 'Cleaned data'!E:E=B17))"),200.0) -> 200 | D17: =IFERROR(__xludf.DUMMYFUNCTION("MAX(FILTER('Cleaned data'!L:L, 'Cleaned data'!E:E=B17))"),607.0) -> 607 | E17: =IFERROR(__xludf.DUMMYFUNCTION("MEDIAN(FILTER('Cleaned data'!L:L, 'Cleaned data'!E:E=B17))"),500.0) -> 500 | F17: =IFERROR(__xludf.DUMMYFUNCTION("MIN(FILTER('Cleaned data'!M:M, 'Cleaned data'!E:E=B17))"),239.0) -> 239 | G17: =IFERROR(__xludf.DUMMYFUNCTION("MAX(FILTER('Cleaned data'!M:M, 'Cleaned data'!E:E=B17))"),391.0) -> 391 | H17: =IFERROR(__xludf.DUMMYFUNCTION("MEDIAN(FILTER('Cleaned data'!M:M, 'Cleaned data'!E:E=B17))"),315.0) -> 315 | I17: =IFERROR(__xludf.DUMMYFUNCTION("MIN(FILTER('Cleaned data'!N:N,'Cleaned data'!E:E=B17))"),210.0) -> 210 | J17: =IFERROR(__xludf.DUMMYFUNCTION("MAX(FILTER('Cleaned data'!N:N,'Cleaned data'!E:E=B17))"),320.0) -> 320 | K17: =IFERROR(__xludf.DUMMYFUNCTION("MEDIAN(FILTER('Cleaned data'!N:N, 'Cleaned data'!E:E=B17))"),300.0) -> 300 | L17: =IFERROR(__xludf.DUMMYFUNCTION("MIN(FILTER('Cleaned data'!O:O, 'Cleaned data'!E:E=B17))"),709.0) -> 709 | M17: =IFERROR(__xludf.DUMMYFUNCTION("INDEX(FILTER('Cleaned data'!B:B, ('Cleaned data'!E:E=B17)*'Cleaned data'!O:O=MIN(FILTER('Cleaned data'!O:O, 'Cleaned data'!E:E=B17))))"),"Caterpillar Inc") -> Caterpillar Inc | N17: =IFERROR(__xludf.DUMMYFUNCTION("MAX(FILTER('Cleaned data'!O:O, 'Cleaned data'!E:E=B17))"),1238.0) -> 1238 | O17: =IFERROR(__xludf.DUMMYFUNCTION("INDEX(FILTER('Cleaned data'!B:B, ('Cleaned data'!E:E=B17)*'Cleaned data'!O:O=MAX(FILTER('Cleaned data'!O:O, 'Cleaned data'!E:E=B17))))"),"Westinghouse Air Brake Technologies Corp") -> Westinghouse Air Brake Technologies Corp | P17: =IFERROR(__xludf.DUMMYFUNCTION("MEDIAN(FILTER('Cleaned data'!O:O, 'Cleaned data'!E:E=B17))"),1125.0) -> 1125 | Q17: =N17-L17 -> 529
A18: =COUNTIF('Cleaned data'!E:E, B18) -> 20 | B18: Consumer products | C18: =IFERROR(__xludf.DUMMYFUNCTION("MIN(FILTER('Cleaned data'!L:L, 'Cleaned data'!E:E=B18))"),200.0) -> 200 | D18: =IFERROR(__xludf.DUMMYFUNCTION("MAX(FILTER('Cleaned data'!L:L, 'Cleaned data'!E:E=B18))"),578.0) -> 578 | E18: =IFERROR(__xludf.DUMMYFUNCTION("MEDIAN(FILTER('Cleaned data'!L:L, 'Cleaned data'!E:E=B18))"),359.0) -> 359 | F18: =IFERROR(__xludf.DUMMYFUNCTION("MIN(FILTER('Cleaned data'!M:M, 'Cleaned data'!E:E=B18))"),203.0) -> 203 | G18: =IFERROR(__xludf.DUMMYFUNCTION("MAX(FILTER('Cleaned data'!M:M, 'Cleaned data'!E:E=B18))"),422.0) -> 422 | H18: =IFERROR(__xludf.DUMMYFUNCTION("MEDIAN(FILTER('Cleaned data'!M:M, 'Cleaned data'!E:E=B18))"),299.0) -> 299 | I18: =IFERROR(__xludf.DUMMYFUNCTION("MIN(FILTER('Cleaned data'!N:N,'Cleaned data'!E:E=B18))"),200.0) -> 200 | J18: =IFERROR(__xludf.DUMMYFUNCTION("MAX(FILTER('Cleaned data'!N:N,'Cleaned data'!E:E=B18))"),348.0) -> 348 | K18: =IFERROR(__xludf.DUMMYFUNCTION("MEDIAN(FILTER('Cleaned data'!N:N, 'Cleaned data'!E:E=B18))"),300.0) -> 300 | L18: =IFERROR(__xludf.DUMMYFUNCTION("MIN(FILTER('Cleaned data'!O:O, 'Cleaned data'!E:E=B18))"),647.0) -> 647 | M18: =IFERROR(__xludf.DUMMYFUNCTION("INDEX(FILTER('Cleaned data'!B:B, ('Cleaned data'!E:E=B18)*'Cleaned data'!O:O=MIN(FILTER('Cleaned data'!O:O, 'Cleaned data'!E:E=B18))))"),"Garmin Ltd") -> Garmin Ltd | N18: =IFERROR(__xludf.DUMMYFUNCTION("MAX(FILTER('Cleaned data'!O:O, 'Cleaned data'!E:E=B18))"),1292.0) -> 1292 | O18: =IFERROR(__xludf.DUMMYFUNCTION("INDEX(FILTER('Cleaned data'!B:B, ('Cleaned data'!E:E=B18)*'Cleaned data'!O:O=MAX(FILTER('Cleaned data'!O:O, 'Cleaned data'!E:E=B18))))"),"Procter & Gamble Co") -> Procter & Gamble Co | P18: =IFERROR(__xludf.DUMMYFUNCTION("MEDIAN(FILTER('Cleaned data'!O:O, 'Cleaned data'!E:E=B18))"),959.0) -> 959 | Q18: =N18-L18 -> 645
A19: =COUNTIF('Cleaned data'!E:E, B19) -> 19 | B19: Chemicals | C19: =IFERROR(__xludf.DUMMYFUNCTION("MIN(FILTER('Cleaned data'!L:L, 'Cleaned data'!E:E=B19))"),205.0) -> 205 | D19: =IFERROR(__xludf.DUMMYFUNCTION("MAX(FILTER('Cleaned data'!L:L, 'Cleaned data'!E:E=B19))"),700.0) -> 700 | E19: =IFERROR(__xludf.DUMMYFUNCTION("MEDIAN(FILTER('Cleaned data'!L:L, 'Cleaned data'!E:E=B19))"),510.0) -> 510 | F19: =IFERROR(__xludf.DUMMYFUNCTION("MIN(FILTER('Cleaned data'!M:M, 'Cleaned data'!E:E=B19))"),201.0) -> 201 | G19: =IFERROR(__xludf.DUMMYFUNCTION("MAX(FILTER('Cleaned data'!M:M, 'Cleaned data'!E:E=B19))"),442.0) -> 442 | H19: =IFERROR(__xludf.DUMMYFUNCTION("MEDIAN(FILTER('Cleaned data'!M:M, 'Cleaned data'!E:E=B19))"),312.0) -> 312 | I19: =IFERROR(__xludf.DUMMYFUNCTION("MIN(FILTER('Cleaned data'!N:N,'Cleaned data'!E:E=B19))"),200.0) -> 200 | J19: =IFERROR(__xludf.DUMMYFUNCTION("MAX(FILTER('Cleaned data'!N:N,'Cleaned data'!E:E=B19))"),330.0) -> 330 | K19: =IFERROR(__xludf.DUMMYFUNCTION("MEDIAN(FILTER('Cleaned data'!N:N, 'Cleaned data'!E:E=B19))"),300.0) -> 300 | L19: =IFERROR(__xludf.DUMMYFUNCTION("MIN(FILTER('Cleaned data'!O:O, 'Cleaned data'!E:E=B19))"),626.0) -> 626 | M19: =IFERROR(__xludf.DUMMYFUNCTION("INDEX(FILTER('Cleaned data'!B:B, ('Cleaned data'!E:E=B19)*'Cleaned data'!O:O=MIN(FILTER('Cleaned data'!O:O, 'Cleaned data'!E:E=B19))))"),"Dow Inc") -> Dow Inc | N19: =IFERROR(__xludf.DUMMYFUNCTION("MAX(FILTER('Cleaned data'!O:O, 'Cleaned data'!E:E=B19))"),1442.0) -> 1442 | O19: =IFERROR(__xludf.DUMMYFUNCTION("INDEX(FILTER('Cleaned data'!B:B, ('Cleaned data'!E:E=B19)*'Cleaned data'!O:O=MAX(FILTER('Cleaned data'!O:O, 'Cleaned data'!E:E=B19))))"),"Air Products and Chemicals Inc") -> Air Products and Chemicals Inc | P19: =IFERROR(__xludf.DUMMYFUNCTION("MEDIAN(FILTER('Cleaned data'!O:O, 'Cleaned data'!E:E=B19))"),1132.0) -> 1132 | Q19: =N19-L19 -> 816
A20: =COUNTIF('Cleaned data'!E:E, B20) -> 16 | B20: Life Sciences Tools and Services | C20: =IFERROR(__xludf.DUMMYFUNCTION("MIN(FILTER('Cleaned data'!L:L, 'Cleaned data'!E:E=B20))"),205.0) -> 205 | D20: =IFERROR(__xludf.DUMMYFUNCTION("MAX(FILTER('Cleaned data'!L:L, 'Cleaned data'!E:E=B20))"),573.0) -> 573 | E20: =IFERROR(__xludf.DUMMYFUNCTION("MEDIAN(FILTER('Cleaned data'!L:L, 'Cleaned data'!E:E=B20))"),510.0) -> 510 | F20: =IFERROR(__xludf.DUMMYFUNCTION("MIN(FILTER('Cleaned data'!M:M, 'Cleaned data'!E:E=B20))"),221.0) -> 221 | G20: =IFERROR(__xludf.DUMMYFUNCTION("MAX(FILTER('Cleaned data'!M:M, 'Cleaned data'!E:E=B20))"),354.0) -> 354 | H20: =IFERROR(__xludf.DUMMYFUNCTION("MEDIAN(FILTER('Cleaned data'!M:M, 'Cleaned data'!E:E=B20))"),301.5) -> 301.5 | I20: =IFERROR(__xludf.DUMMYFUNCTION("MIN(FILTER('Cleaned data'!N:N,'Cleaned data'!E:E=B20))"),215.0) -> 215 | J20: =IFERROR(__xludf.DUMMYFUNCTION("MAX(FILTER('Cleaned data'!N:N,'Cleaned data'!E:E=B20))"),385.0) -> 385 | K20: =IFERROR(__xludf.DUMMYFUNCTION("MEDIAN(FILTER('Cleaned data'!N:N, 'Cleaned data'!E:E=B20))"),270.0) -> 270 | L20: =IFERROR(__xludf.DUMMYFUNCTION("MIN(FILTER('Cleaned data'!O:O, 'Cleaned data'!E:E=B20))"),659.0) -> 659 | M20: =IFERROR(__xludf.DUMMYFUNCTION("INDEX(FILTER('Cleaned data'!B:B, ('Cleaned data'!E:E=B20)*'Cleaned data'!O:O=MIN(FILTER('Cleaned data'!O:O, 'Cleaned data'!E:E=B20))))"),"Absci Corp") -> Absci Corp | N20: =IFERROR(__xludf.DUMMYFUNCTION("MAX(FILTER('Cleaned data'!O:O, 'Cleaned data'!E:E=B20))"),1259.0) -> 1259 | O20: =IFERROR(__xludf.DUMMYFUNCTION("INDEX(FILTER('Cleaned data'!B:B, ('Cleaned data'!E:E=B20)*'Cleaned data'!O:O=MAX(FILTER('Cleaned data'!O:O, 'Cleaned data'!E:E=B20))))"),"Danaher Corp") -> Danaher Corp | P20: =IFERROR(__xludf.DUMMYFUNCTION("MEDIAN(FILTER('Cleaned data'!O:O, 'Cleaned data'!E:E=B20))"),1041.0) -> 1041 | Q20: =N20-L20 -> 600
A21: =COUNTIF('Cleaned data'!E:E, B21) -> 14 | B21: Food Products | C21: =IFERROR(__xludf.DUMMYFUNCTION("MIN(FILTER('Cleaned data'!L:L, 'Cleaned data'!E:E=B21))"),345.0) -> 345 | D21: =IFERROR(__xludf.DUMMYFUNCTION("MAX(FILTER('Cleaned data'!L:L, 'Cleaned data'!E:E=B21))"),587.0) -> 587 | E21: =IFERROR(__xludf.DUMMYFUNCTION("MEDIAN(FILTER('Cleaned data'!L:L, 'Cleaned data'!E:E=B21))"),520.0) -> 520 | F21: =IFERROR(__xludf.DUMMYFUNCTION("MIN(FILTER('Cleaned data'!M:M, 'Cleaned data'!E:E=B21))"),248.0) -> 248 | G21: =IFERROR(__xludf.DUMMYFUNCTION("MAX(FILTER('Cleaned data'!M:M, 'Cleaned data'!E:E=B21))"),374.0) -> 374 | H21: =IFERROR(__xludf.DUMMYFUNCTION("MEDIAN(FILTER('Cleaned data'!M:M, 'Cleaned data'!E:E=B21))"),304.0) -> 304 | I21: =IFERROR(__xludf.DUMMYFUNCTION("MIN(FILTER('Cleaned data'!N:N,'Cleaned data'!E:E=B21))"),220.0) -> 220 | J21: =IFERROR(__xludf.DUMMYFUNCTION("MAX(FILTER('Cleaned data'!N:N,'Cleaned data'!E:E=B21))"),365.0) -> 365 | K21: =IFERROR(__xludf.DUMMYFUNCTION("MEDIAN(FILTER('Cleaned data'!N:N, 'Cleaned data'!E:E=B21))"),300.0) -> 300 | L21: =IFERROR(__xludf.DUMMYFUNCTION("MIN(FILTER('Cleaned data'!O:O, 'Cleaned data'!E:E=B21))"),901.0) -> 901 | M21: =IFERROR(__xludf.DUMMYFUNCTION("INDEX(FILTER('Cleaned data'!B:B, ('Cleaned data'!E:E=B21)*'Cleaned data'!O:O=MIN(FILTER('Cleaned data'!O:O, 'Cleaned data'!E:E=B21))))"),"Lamb Weston Holdings Inc") -> Lamb Weston Holdings Inc | N21: =IFERROR(__xludf.DUMMYFUNCTION("MAX(FILTER('Cleaned data'!O:O, 'Cleaned data'!E:E=B21))"),1276.0) -> 1276 | O21: =IFERROR(__xludf.DUMMYFUNCTION("INDEX(FILTER('Cleaned data'!B:B, ('Cleaned data'!E:E=B21)*'Cleaned data'!O:O=MAX(FILTER('Cleaned data'!O:O, 'Cleaned data'!E:E=B21))))"),"General Mills Inc") -> General Mills Inc | P21: =IFERROR(__xludf.DUMMYFUNCTION("MEDIAN(FILTER('Cleaned data'!O:O, 'Cleaned data'!E:E=B21))"),1127.0) -> 1127 | Q21: =N21-L21 -> 375
A22: =COUNTIF('Cleaned data'!E:E, B22) -> 11 | B22: Aerospace and Defense | C22: =IFERROR(__xludf.DUMMYFUNCTION("MIN(FILTER('Cleaned data'!L:L, 'Cleaned data'!E:E=B22))"),220.0) -> 220 | D22: =IFERROR(__xludf.DUMMYFUNCTION("MAX(FILTER('Cleaned data'!L:L, 'Cleaned data'!E:E=B22))"),545.0) -> 545 | E22: =IFERROR(__xludf.DUMMYFUNCTION("MEDIAN(FILTER('Cleaned data'!L:L, 'Cleaned data'!E:E=B22))"),510.0) -> 510 | F22: =IFERROR(__xludf.DUMMYFUNCTION("MIN(FILTER('Cleaned data'!M:M, 'Cleaned data'!E:E=B22))"),203.0) -> 203 | G22: =IFERROR(__xludf.DUMMYFUNCTION("MAX(FILTER('Cleaned data'!M:M, 'Cleaned data'!E:E=B22))"),337.0) -> 337 | H22: =IFERROR(__xludf.DUMMYFUNCTION("MEDIAN(FILTER('Cleaned data'!M:M, 'Cleaned data'!E:E=B22))"),310.0) -> 310 | I22: =IFERROR(__xludf.DUMMYFUNCTION("MIN(FILTER('Cleaned data'!N:N,'Cleaned data'!E:E=B22))"),200.0) -> 200 | J22: =IFERROR(__xludf.DUMMYFUNCTION("MAX(FILTER('Cleaned data'!N:N,'Cleaned data'!E:E=B22))"),400.0) -> 400 | K22: =IFERROR(__xludf.DUMMYFUNCTION("MEDIAN(FILTER('Cleaned data'!N:N, 'Cleaned data'!E:E=B22))"),300.0) -> 300 | L22: =IFERROR(__xludf.DUMMYFUNCTION("MIN(FILTER('Cleaned data'!O:O, 'Cleaned data'!E:E=B22))"),633.0) -> 633 | M22: =IFERROR(__xludf.DUMMYFUNCTION("INDEX(FILTER('Cleaned data'!B:B, ('Cleaned data'!E:E=B22)*'Cleaned data'!O:O=MIN(FILTER('Cleaned data'!O:O, 'Cleaned data'!E:E=B22))))"),"HEICO Corp") -> HEICO Corp | N22: =IFERROR(__xludf.DUMMYFUNCTION("MAX(FILTER('Cleaned data'!O:O, 'Cleaned data'!E:E=B22))"),1250.0) -> 1250 | O22: =IFERROR(__xludf.DUMMYFUNCTION("INDEX(FILTER('Cleaned data'!B:B, ('Cleaned data'!E:E=B22)*'Cleaned data'!O:O=MAX(FILTER('Cleaned data'!O:O, 'Cleaned data'!E:E=B22))))"),"Raytheon Technologies Corp") -> Raytheon Technologies Corp | P22: =IFERROR(__xludf.DUMMYFUNCTION("MEDIAN(FILTER('Cleaned data'!O:O, 'Cleaned data'!E:E=B22))"),1120.0) -> 1120 | Q22: =N22-L22 -> 617
A23: =COUNTIF('Cleaned data'!E:E, B23) -> 10 | B23: Metals and Mining | C23: =IFERROR(__xludf.DUMMYFUNCTION("MIN(FILTER('Cleaned data'!L:L, 'Cleaned data'!E:E=B23))"),215.0) -> 215 | D23: =IFERROR(__xludf.DUMMYFUNCTION("MAX(FILTER('Cleaned data'!L:L, 'Cleaned data'!E:E=B23))"),675.0) -> 675 | E23: =IFERROR(__xludf.DUMMYFUNCTION("MEDIAN(FILTER('Cleaned data'!L:L, 'Cleaned data'!E:E=B23))"),450.0) -> 450 | F23: =IFERROR(__xludf.DUMMYFUNCTION("MIN(FILTER('Cleaned data'!M:M, 'Cleaned data'!E:E=B23))"),200.0) -> 200 | G23: =IFERROR(__xludf.DUMMYFUNCTION("MAX(FILTER('Cleaned data'!M:M, 'Cleaned data'!E:E=B23))"),389.0) -> 389 | H23: =IFERROR(__xludf.DUMMYFUNCTION("MEDIAN(FILTER('Cleaned data'!M:M, 'Cleaned data'!E:E=B23))"),301.5) -> 301.5 | I23: =IFERROR(__xludf.DUMMYFUNCTION("MIN(FILTER('Cleaned data'!N:N,'Cleaned data'!E:E=B23))"),200.0) -> 200 | J23: =IFERROR(__xludf.DUMMYFUNCTION("MAX(FILTER('Cleaned data'!N:N,'Cleaned data'!E:E=B23))"),355.0) -> 355 | K23: =IFERROR(__xludf.DUMMYFUNCTION("MEDIAN(FILTER('Cleaned data'!N:N, 'Cleaned data'!E:E=B23))"),300.0) -> 300 | L23: =IFERROR(__xludf.DUMMYFUNCTION("MIN(FILTER('Cleaned data'!O:O, 'Cleaned data'!E:E=B23))"),615.0) -> 615 | M23: =IFERROR(__xludf.DUMMYFUNCTION("INDEX(FILTER('Cleaned data'!B:B, ('Cleaned data'!E:E=B23)*'Cleaned data'!O:O=MIN(FILTER('Cleaned data'!O:O, 'Cleaned data'!E:E=B23))))"),"Warrior Met Coal Inc") -> Warrior Met Coal Inc | N23: =IFERROR(__xludf.DUMMYFUNCTION("MAX(FILTER('Cleaned data'!O:O, 'Cleaned data'!E:E=B23))"),1419.0) -> 1419 | O23: =IFERROR(__xludf.DUMMYFUNCTION("INDEX(FILTER('Cleaned data'!B:B, ('Cleaned data'!E:E=B23)*'Cleaned data'!O:O=MAX(FILTER('Cleaned data'!O:O, 'Cleaned data'!E:E=B23))))"),"Newmont Corporation") -> Newmont Corporation | P23: =IFERROR(__xludf.DUMMYFUNCTION("MEDIAN(FILTER('Cleaned data'!O:O, 'Cleaned data'!E:E=B23))"),1020.5) -> 1020.5 | Q23: =N23-L23 -> 804
A24: =COUNTIF('Cleaned data'!E:E, B24) -> 10 | B24: Building | C24: =IFERROR(__xludf.DUMMYFUNCTION("MIN(FILTER('Cleaned data'!L:L, 'Cleaned data'!E:E=B24))"),210.0) -> 210 | D24: =IFERROR(__xludf.DUMMYFUNCTION("MAX(FILTER('Cleaned data'!L:L, 'Cleaned data'!E:E=B24))"),700.0) -> 700 | E24: =IFERROR(__xludf.DUMMYFUNCTION("MEDIAN(FILTER('Cleaned data'!L:L, 'Cleaned data'!E:E=B24))"),510.0) -> 510 | F24: =IFERROR(__xludf.DUMMYFUNCTION("MIN(FILTER('Cleaned data'!M:M, 'Cleaned data'!E:E=B24))"),237.0) -> 237 | G24: =IFERROR(__xludf.DUMMYFUNCTION("MAX(FILTER('Cleaned data'!M:M, 'Cleaned data'!E:E=B24))"),389.0) -> 389 | H24: =IFERROR(__xludf.DUMMYFUNCTION("MEDIAN(FILTER('Cleaned data'!M:M, 'Cleaned data'!E:E=B24))"),303.5) -> 303.5 | I24: =IFERROR(__xludf.DUMMYFUNCTION("MIN(FILTER('Cleaned data'!N:N,'Cleaned data'!E:E=B24))"),223.0) -> 223 | J24: =IFERROR(__xludf.DUMMYFUNCTION("MAX(FILTER('Cleaned data'!N:N,'Cleaned data'!E:E=B24))"),325.0) -> 325 | K24: =IFERROR(__xludf.DUMMYFUNCTION("MEDIAN(FILTER('Cleaned data'!N:N, 'Cleaned data'!E:E=B24))"),302.5) -> 302.5 | L24: =IFERROR(__xludf.DUMMYFUNCTION("MIN(FILTER('Cleaned data'!O:O, 'Cleaned data'!E:E=B24))"),694.0) -> 694 | M24: =IFERROR(__xludf.DUMMYFUNCTION("INDEX(FILTER('Cleaned data'!B:B, ('Cleaned data'!E:E=B24)*'Cleaned data'!O:O=MIN(FILTER('Cleaned data'!O:O, 'Cleaned data'!E:E=B24))))"),"Carrier Global Corp") -> Carrier Global Corp | N24: =IFERROR(__xludf.DUMMYFUNCTION("MAX(FILTER('Cleaned data'!O:O, 'Cleaned data'!E:E=B24))"),1409.0) -> 1409 | O24: =IFERROR(__xludf.DUMMYFUNCTION("INDEX(FILTER('Cleaned data'!B:B, ('Cleaned data'!E:E=B24)*'Cleaned data'!O:O=MAX(FILTER('Cleaned data'!O:O, 'Cleaned data'!E:E=B24))))"),"Trane Technologies PLC") -> Trane Technologies PLC | P24: =IFERROR(__xludf.DUMMYFUNCTION("MEDIAN(FILTER('Cleaned data'!O:O, 'Cleaned data'!E:E=B24))"),1123.5) -> 1123.5 | Q24: =N24-L24 -> 715
A25: =COUNTIF('Cleaned data'!E:E, B25) -> 9 | B25: Communications | C25: =IFERROR(__xludf.DUMMYFUNCTION("MIN(FILTER('Cleaned data'!L:L, 'Cleaned data'!E:E=B25))"),200.0) -> 200 | D25: =IFERROR(__xludf.DUMMYFUNCTION("MAX(FILTER('Cleaned data'!L:L, 'Cleaned data'!E:E=B25))"),510.0) -> 510 | E25: =IFERROR(__xludf.DUMMYFUNCTION("MEDIAN(FILTER('Cleaned data'!L:L, 'Cleaned data'!E:E=B25))"),370.0) -> 370 | F25: =IFERROR(__xludf.DUMMYFUNCTION("MIN(FILTER('Cleaned data'!M:M, 'Cleaned data'!E:E=B25))"),221.0) -> 221 | G25: =IFERROR(__xludf.DUMMYFUNCTION("MAX(FILTER('Cleaned data'!M:M, 'Cleaned data'!E:E=B25))"),337.0) -> 337 | H25: =IFERROR(__xludf.DUMMYFUNCTION("MEDIAN(FILTER('Cleaned data'!M:M, 'Cleaned data'!E:E=B25))"),305.0) -> 305 | I25: =IFERROR(__xludf.DUMMYFUNCTION("MIN(FILTER('Cleaned data'!N:N,'Cleaned data'!E:E=B25))"),210.0) -> 210 | J25: =IFERROR(__xludf.DUMMYFUNCTION("MAX(FILTER('Cleaned data'!N:N,'Cleaned data'!E:E=B25))"),365.0) -> 365 | K25: =IFERROR(__xludf.DUMMYFUNCTION("MEDIAN(FILTER('Cleaned data'!N:N, 'Cleaned data'!E:E=B25))"),295.0) -> 295 | L25: =IFERROR(__xludf.DUMMYFUNCTION("MIN(FILTER('Cleaned data'!O:O, 'Cleaned data'!E:E=B25))"),636.0) -> 636 | M25: =IFERROR(__xludf.DUMMYFUNCTION("INDEX(FILTER('Cleaned data'!B:B, ('Cleaned data'!E:E=B25)*'Cleaned data'!O:O=MIN(FILTER('Cleaned data'!O:O, 'Cleaned data'!E:E=B25))))"),"F5 Inc") -> F5 Inc | N25: =IFERROR(__xludf.DUMMYFUNCTION("MAX(FILTER('Cleaned data'!O:O, 'Cleaned data'!E:E=B25))"),1157.0) -> 1157 | O25: =IFERROR(__xludf.DUMMYFUNCTION("INDEX(FILTER('Cleaned data'!B:B, ('Cleaned data'!E:E=B25)*'Cleaned data'!O:O=MAX(FILTER('Cleaned data'!O:O, 'Cleaned data'!E:E=B25))))"),"Motorola Solutions Inc") -> Motorola Solutions Inc | P25: =IFERROR(__xludf.DUMMYFUNCTION("MEDIAN(FILTER('Cleaned data'!O:O, 'Cleaned data'!E:E=B25))"),1015.0) -> 1015 | Q25: =N25-L25 -> 521
A26: =COUNTIF('Cleaned data'!E:E, B26) -> 9 | B26: Textiles Apparel and Luxury Goods | C26: =IFERROR(__xludf.DUMMYFUNCTION("MIN(FILTER('Cleaned data'!L:L, 'Cleaned data'!E:E=B26))"),200.0) -> 200 | D26: =IFERROR(__xludf.DUMMYFUNCTION("MAX(FILTER('Cleaned data'!L:L, 'Cleaned data'!E:E=B26))"),508.0) -> 508 | E26: =IFERROR(__xludf.DUMMYFUNCTION("MEDIAN(FILTER('Cleaned data'!L:L, 'Cleaned data'!E:E=B26))"),418.0) -> 418 | F26: =IFERROR(__xludf.DUMMYFUNCTION("MIN(FILTER('Cleaned data'!M:M, 'Cleaned data'!E:E=B26))"),211.0) -> 211 | G26: =IFERROR(__xludf.DUMMYFUNCTION("MAX(FILTER('Cleaned data'!M:M, 'Cleaned data'!E:E=B26))"),352.0) -> 352 | H26: =IFERROR(__xludf.DUMMYFUNCTION("MEDIAN(FILTER('Cleaned data'!M:M, 'Cleaned data'!E:E=B26))"),298.0) -> 298 | I26: =IFERROR(__xludf.DUMMYFUNCTION("MIN(FILTER('Cleaned data'!N:N,'Cleaned data'!E:E=B26))"),200.0) -> 200 | J26: =IFERROR(__xludf.DUMMYFUNCTION("MAX(FILTER('Cleaned data'!N:N,'Cleaned data'!E:E=B26))"),315.0) -> 315 | K26: =IFERROR(__xludf.DUMMYFUNCTION("MEDIAN(FILTER('Cleaned data'!N:N, 'Cleaned data'!E:E=B26))"),300.0) -> 300 | L26: =IFERROR(__xludf.DUMMYFUNCTION("MIN(FILTER('Cleaned data'!O:O, 'Cleaned data'!E:E=B26))"),621.0) -> 621 | M26: =IFERROR(__xludf.DUMMYFUNCTION("INDEX(FILTER('Cleaned data'!B:B, ('Cleaned data'!E:E=B26)*'Cleaned data'!O:O=MIN(FILTER('Cleaned data'!O:O, 'Cleaned data'!E:E=B26))))"),"Ever-Glory International Group Inc") -> Ever-Glory International Group Inc | N26: =IFERROR(__xludf.DUMMYFUNCTION("MAX(FILTER('Cleaned data'!O:O, 'Cleaned data'!E:E=B26))"),1106.0) -> 1106 | O26: =IFERROR(__xludf.DUMMYFUNCTION("INDEX(FILTER('Cleaned data'!B:B, ('Cleaned data'!E:E=B26)*'Cleaned data'!O:O=MAX(FILTER('Cleaned data'!O:O, 'Cleaned data'!E:E=B26))))"),"VF Corp") -> VF Corp | P26: =IFERROR(__xludf.DUMMYFUNCTION("MEDIAN(FILTER('Cleaned data'!O:O, 'Cleaned data'!E:E=B26))"),1039.0) -> 1039 | Q26: =N26-L26 -> 485
A27: =COUNTIF('Cleaned data'!E:E, B27) -> 7 | B27: Commercial Services and Supplies | C27: =IFERROR(__xludf.DUMMYFUNCTION("MIN(FILTER('Cleaned data'!L:L, 'Cleaned data'!E:E=B27))"),235.0) -> 235 | D27: =IFERROR(__xludf.DUMMYFUNCTION("MAX(FILTER('Cleaned data'!L:L, 'Cleaned data'!E:E=B27))"),613.0) -> 613 | E27: =IFERROR(__xludf.DUMMYFUNCTION("MEDIAN(FILTER('Cleaned data'!L:L, 'Cleaned data'!E:E=B27))"),500.0) -> 500 | F27: =IFERROR(__xludf.DUMMYFUNCTION("MIN(FILTER('Cleaned data'!M:M, 'Cleaned data'!E:E=B27))"),204.0) -> 204 | G27: =IFERROR(__xludf.DUMMYFUNCTION("MAX(FILTER('Cleaned data'!M:M, 'Cleaned data'!E:E=B27))"),408.0) -> 408 | H27: =IFERROR(__xludf.DUMMYFUNCTION("MEDIAN(FILTER('Cleaned data'!M:M, 'Cleaned data'!E:E=B27))"),300.0) -> 300 | I27: =IFERROR(__xludf.DUMMYFUNCTION("MIN(FILTER('Cleaned data'!N:N,'Cleaned data'!E:E=B27))"),205.0) -> 205 | J27: =IFERROR(__xludf.DUMMYFUNCTION("MAX(FILTER('Cleaned data'!N:N,'Cleaned data'!E:E=B27))"),315.0) -> 315 | K27: =IFERROR(__xludf.DUMMYFUNCTION("MEDIAN(FILTER('Cleaned data'!N:N, 'Cleaned data'!E:E=B27))"),300.0) -> 300 | L27: =IFERROR(__xludf.DUMMYFUNCTION("MIN(FILTER('Cleaned data'!O:O, 'Cleaned data'!E:E=B27))"),679.0) -> 679 | M27: =IFERROR(__xludf.DUMMYFUNCTION("INDEX(FILTER('Cleaned data'!B:B, ('Cleaned data'!E:E=B27)*'Cleaned data'!O:O=MIN(FILTER('Cleaned data'!O:O, 'Cleaned data'!E:E=B27))))"),"Copart Inc") -> Copart Inc | N27: =IFERROR(__xludf.DUMMYFUNCTION("MAX(FILTER('Cleaned data'!O:O, 'Cleaned data'!E:E=B27))"),1306.0) -> 1306 | O27: =IFERROR(__xludf.DUMMYFUNCTION("INDEX(FILTER('Cleaned data'!B:B, ('Cleaned data'!E:E=B27)*'Cleaned data'!O:O=MAX(FILTER('Cleaned data'!O:O, 'Cleaned data'!E:E=B27))))"),"Waste Management Inc") -> Waste Management Inc | P27: =IFERROR(__xludf.DUMMYFUNCTION("MEDIAN(FILTER('Cleaned data'!O:O, 'Cleaned data'!E:E=B27))"),1100.0) -> 1100 | Q27: =N27-L27 -> 627
A28: =COUNTIF('Cleaned data'!E:E, B28) -> 7 | B28: Airlines | C28: =IFERROR(__xludf.DUMMYFUNCTION("MIN(FILTER('Cleaned data'!L:L, 'Cleaned data'!E:E=B28))"),200.0) -> 200 | D28: =IFERROR(__xludf.DUMMYFUNCTION("MAX(FILTER('Cleaned data'!L:L, 'Cleaned data'!E:E=B28))"),515.0) -> 515 | E28: =IFERROR(__xludf.DUMMYFUNCTION("MEDIAN(FILTER('Cleaned data'!L:L, 'Cleaned data'!E:E=B28))"),287.0) -> 287 | F28: =IFERROR(__xludf.DUMMYFUNCTION("MIN(FILTER('Cleaned data'!M:M, 'Cleaned data'!E:E=B28))"),203.0) -> 203 | G28: =IFERROR(__xludf.DUMMYFUNCTION("MAX(FILTER('Cleaned data'!M:M, 'Cleaned data'!E:E=B28))"),321.0) -> 321 | H28: =IFERROR(__xludf.DUMMYFUNCTION("MEDIAN(FILTER('Cleaned data'!M:M, 'Cleaned data'!E:E=B28))"),300.0) -> 300 | I28: =IFERROR(__xludf.DUMMYFUNCTION("MIN(FILTER('Cleaned data'!N:N,'Cleaned data'!E:E=B28))"),200.0) -> 200 | J28: =IFERROR(__xludf.DUMMYFUNCTION("MAX(FILTER('Cleaned data'!N:N,'Cleaned data'!E:E=B28))"),313.0) -> 313 | K28: =IFERROR(__xludf.DUMMYFUNCTION("MEDIAN(FILTER('Cleaned data'!N:N, 'Cleaned data'!E:E=B28))"),248.0) -> 248 | L28: =IFERROR(__xludf.DUMMYFUNCTION("MIN(FILTER('Cleaned data'!O:O, 'Cleaned data'!E:E=B28))"),629.0) -> 629 | M28: =IFERROR(__xludf.DUMMYFUNCTION("INDEX(FILTER('Cleaned data'!B:B, ('Cleaned data'!E:E=B28)*'Cleaned data'!O:O=MIN(FILTER('Cleaned data'!O:O, 'Cleaned data'!E:E=B28))))"),"United Airlines Holdings Inc") -> United Airlines Holdings Inc | N28: =IFERROR(__xludf.DUMMYFUNCTION("MAX(FILTER('Cleaned data'!O:O, 'Cleaned data'!E:E=B28))"),1128.0) -> 1128 | O28: =IFERROR(__xludf.DUMMYFUNCTION("INDEX(FILTER('Cleaned data'!B:B, ('Cleaned data'!E:E=B28)*'Cleaned data'!O:O=MAX(FILTER('Cleaned data'!O:O, 'Cleaned data'!E:E=B28))))"),"Delta Air Lines Inc") -> Delta Air Lines Inc | P28: =IFERROR(__xludf.DUMMYFUNCTION("MEDIAN(FILTER('Cleaned data'!O:O, 'Cleaned data'!E:E=B28))"),746.0) -> 746 | Q28: =N28-L28 -> 499
A29: =COUNTIF('Cleaned data'!E:E, B29) -> 7 | B29: Professional Services | C29: =IFERROR(__xludf.DUMMYFUNCTION("MIN(FILTER('Cleaned data'!L:L, 'Cleaned data'!E:E=B29))"),255.0) -> 255 | D29: =IFERROR(__xludf.DUMMYFUNCTION("MAX(FILTER('Cleaned data'!L:L, 'Cleaned data'!E:E=B29))"),615.0) -> 615 | E29: =IFERROR(__xludf.DUMMYFUNCTION("MEDIAN(FILTER('Cleaned data'!L:L, 'Cleaned data'!E:E=B29))"),500.0) -> 500 | F29: =IFERROR(__xludf.DUMMYFUNCTION("MIN(FILTER('Cleaned data'!M:M, 'Cleaned data'!E:E=B29))"),264.0) -> 264 | G29: =IFERROR(__xludf.DUMMYFUNCTION("MAX(FILTER('Cleaned data'!M:M, 'Cleaned data'!E:E=B29))"),366.0) -> 366 | H29: =IFERROR(__xludf.DUMMYFUNCTION("MEDIAN(FILTER('Cleaned data'!M:M, 'Cleaned data'!E:E=B29))"),310.0) -> 310 | I29: =IFERROR(__xludf.DUMMYFUNCTION("MIN(FILTER('Cleaned data'!N:N,'Cleaned data'!E:E=B29))"),278.0) -> 278 | J29: =IFERROR(__xludf.DUMMYFUNCTION("MAX(FILTER('Cleaned data'!N:N,'Cleaned data'!E:E=B29))"),310.0) -> 310 | K29: =IFERROR(__xludf.DUMMYFUNCTION("MEDIAN(FILTER('Cleaned data'!N:N, 'Cleaned data'!E:E=B29))"),300.0) -> 300 | L29: =IFERROR(__xludf.DUMMYFUNCTION("MIN(FILTER('Cleaned data'!O:O, 'Cleaned data'!E:E=B29))"),817.0) -> 817 | M29: =IFERROR(__xludf.DUMMYFUNCTION("INDEX(FILTER('Cleaned data'!B:B, ('Cleaned data'!E:E=B29)*'Cleaned data'!O:O=MIN(FILTER('Cleaned data'!O:O, 'Cleaned data'!E:E=B29))))"),"Upwork Inc") -> Upwork Inc | N29: =IFERROR(__xludf.DUMMYFUNCTION("MAX(FILTER('Cleaned data'!O:O, 'Cleaned data'!E:E=B29))"),1281.0) -> 1281 | O29: =IFERROR(__xludf.DUMMYFUNCTION("INDEX(FILTER('Cleaned data'!B:B, ('Cleaned data'!E:E=B29)*'Cleaned data'!O:O=MAX(FILTER('Cleaned data'!O:O, 'Cleaned data'!E:E=B29))))"),"Verisk Analytics Inc") -> Verisk Analytics Inc | P29: =IFERROR(__xludf.DUMMYFUNCTION("MEDIAN(FILTER('Cleaned data'!O:O, 'Cleaned data'!E:E=B29))"),1100.0) -> 1100 | Q29: =N29-L29 -> 464
A30: =COUNTIF('Cleaned data'!E:E, B30) -> 6 | B30: Construction | C30: =IFERROR(__xludf.DUMMYFUNCTION("MIN(FILTER('Cleaned data'!L:L, 'Cleaned data'!E:E=B30))"),200.0) -> 200 | D30: =IFERROR(__xludf.DUMMYFUNCTION("MAX(FILTER('Cleaned data'!L:L, 'Cleaned data'!E:E=B30))"),589.0) -> 589 | E30: =IFERROR(__xludf.DUMMYFUNCTION("MEDIAN(FILTER('Cleaned data'!L:L, 'Cleaned data'!E:E=B30))"),555.0) -> 555 | F30: =IFERROR(__xludf.DUMMYFUNCTION("MIN(FILTER('Cleaned data'!M:M, 'Cleaned data'!E:E=B30))"),200.0) -> 200 | G30: =IFERROR(__xludf.DUMMYFUNCTION("MAX(FILTER('Cleaned data'!M:M, 'Cleaned data'!E:E=B30))"),390.0) -> 390 | H30: =IFERROR(__xludf.DUMMYFUNCTION("MEDIAN(FILTER('Cleaned data'!M:M, 'Cleaned data'!E:E=B30))"),316.0) -> 316 | I30: =IFERROR(__xludf.DUMMYFUNCTION("MIN(FILTER('Cleaned data'!N:N,'Cleaned data'!E:E=B30))"),200.0) -> 200 | J30: =IFERROR(__xludf.DUMMYFUNCTION("MAX(FILTER('Cleaned data'!N:N,'Cleaned data'!E:E=B30))"),310.0) -> 310 | K30: =IFERROR(__xludf.DUMMYFUNCTION("MEDIAN(FILTER('Cleaned data'!N:N, 'Cleaned data'!E:E=B30))"),300.0) -> 300 | L30: =IFERROR(__xludf.DUMMYFUNCTION("MIN(FILTER('Cleaned data'!O:O, 'Cleaned data'!E:E=B30))"),600.0) -> 600 | M30: =IFERROR(__xludf.DUMMYFUNCTION("INDEX(FILTER('Cleaned data'!B:B, ('Cleaned data'!E:E=B30)*'Cleaned data'!O:O=MIN(FILTER('Cleaned data'!O:O, 'Cleaned data'!E:E=B30))))"),"Granite Construction Inc") -> Granite Construction Inc | N30: =IFERROR(__xludf.DUMMYFUNCTION("MAX(FILTER('Cleaned data'!O:O, 'Cleaned data'!E:E=B30))"),1256.0) -> 1256 | O30: =IFERROR(__xludf.DUMMYFUNCTION("INDEX(FILTER('Cleaned data'!B:B, ('Cleaned data'!E:E=B30)*'Cleaned data'!O:O=MAX(FILTER('Cleaned data'!O:O, 'Cleaned data'!E:E=B30))))"),"Matrix Service Co") -> Matrix Service Co | P30: =IFERROR(__xludf.DUMMYFUNCTION("MEDIAN(FILTER('Cleaned data'!O:O, 'Cleaned data'!E:E=B30))"),1187.5) -> 1187.5 | Q30: =N30-L30 -> 656
A31: =COUNTIF('Cleaned data'!E:E, B31) -> 6 | B31: Logistics and Transportation | C31: =IFERROR(__xludf.DUMMYFUNCTION("MIN(FILTER('Cleaned data'!L:L, 'Cleaned data'!E:E=B31))"),234.0) -> 234 | D31: =IFERROR(__xludf.DUMMYFUNCTION("MAX(FILTER('Cleaned data'!L:L, 'Cleaned data'!E:E=B31))"),575.0) -> 575 | E31: =IFERROR(__xludf.DUMMYFUNCTION("MEDIAN(FILTER('Cleaned data'!L:L, 'Cleaned data'!E:E=B31))"),515.0) -> 515 | F31: =IFERROR(__xludf.DUMMYFUNCTION("MIN(FILTER('Cleaned data'!M:M, 'Cleaned data'!E:E=B31))"),210.0) -> 210 | G31: =IFERROR(__xludf.DUMMYFUNCTION("MAX(FILTER('Cleaned data'!M:M, 'Cleaned data'!E:E=B31))"),374.0) -> 374 | H31: =IFERROR(__xludf.DUMMYFUNCTION("MEDIAN(FILTER('Cleaned data'!M:M, 'Cleaned data'!E:E=B31))"),290.0) -> 290 | I31: =IFERROR(__xludf.DUMMYFUNCTION("MIN(FILTER('Cleaned data'!N:N,'Cleaned data'!E:E=B31))"),237.0) -> 237 | J31: =IFERROR(__xludf.DUMMYFUNCTION("MAX(FILTER('Cleaned data'!N:N,'Cleaned data'!E:E=B31))"),338.0) -> 338 | K31: =IFERROR(__xludf.DUMMYFUNCTION("MEDIAN(FILTER('Cleaned data'!N:N, 'Cleaned data'!E:E=B31))"),277.5) -> 277.5 | L31: =IFERROR(__xludf.DUMMYFUNCTION("MIN(FILTER('Cleaned data'!O:O, 'Cleaned data'!E:E=B31))"),769.0) -> 769 | M31: =IFERROR(__xludf.DUMMYFUNCTION("INDEX(FILTER('Cleaned data'!B:B, ('Cleaned data'!E:E=B31)*'Cleaned data'!O:O=MIN(FILTER('Cleaned data'!O:O, 'Cleaned data'!E:E=B31))))"),"Air T Inc") -> Air T Inc | N31: =IFERROR(__xludf.DUMMYFUNCTION("MAX(FILTER('Cleaned data'!O:O, 'Cleaned data'!E:E=B31))"),1243.0) -> 1243 | O31: =IFERROR(__xludf.DUMMYFUNCTION("INDEX(FILTER('Cleaned data'!B:B, ('Cleaned data'!E:E=B31)*'Cleaned data'!O:O=MAX(FILTER('Cleaned data'!O:O, 'Cleaned data'!E:E=B31))))"),"CH Robinson Worldwide Inc") -> CH Robinson Worldwide Inc | P31: =IFERROR(__xludf.DUMMYFUNCTION("MEDIAN(FILTER('Cleaned data'!O:O, 'Cleaned data'!E:E=B31))"),1056.0) -> 1056 | Q31: =N31-L31 -> 474
A32: =COUNTIF('Cleaned data'!E:E, B32) -> 6 | B32: Road and Rail | C32: =IFERROR(__xludf.DUMMYFUNCTION("MIN(FILTER('Cleaned data'!L:L, 'Cleaned data'!E:E=B32))"),290.0) -> 290 | D32: =IFERROR(__xludf.DUMMYFUNCTION("MAX(FILTER('Cleaned data'!L:L, 'Cleaned data'!E:E=B32))"),560.0) -> 560 | E32: =IFERROR(__xludf.DUMMYFUNCTION("MEDIAN(FILTER('Cleaned data'!L:L, 'Cleaned data'!E:E=B32))"),488.5) -> 488.5 | F32: =IFERROR(__xludf.DUMMYFUNCTION("MIN(FILTER('Cleaned data'!M:M, 'Cleaned data'!E:E=B32))"),257.0) -> 257 | G32: =IFERROR(__xludf.DUMMYFUNCTION("MAX(FILTER('Cleaned data'!M:M, 'Cleaned data'!E:E=B32))"),423.0) -> 423 | H32: =IFERROR(__xludf.DUMMYFUNCTION("MEDIAN(FILTER('Cleaned data'!M:M, 'Cleaned data'!E:E=B32))"),314.5) -> 314.5 | I32: =IFERROR(__xludf.DUMMYFUNCTION("MIN(FILTER('Cleaned data'!N:N,'Cleaned data'!E:E=B32))"),245.0) -> 245 | J32: =IFERROR(__xludf.DUMMYFUNCTION("MAX(FILTER('Cleaned data'!N:N,'Cleaned data'!E:E=B32))"),330.0) -> 330 | K32: =IFERROR(__xludf.DUMMYFUNCTION("MEDIAN(FILTER('Cleaned data'!N:N, 'Cleaned data'!E:E=B32))"),301.5) -> 301.5 | L32: =IFERROR(__xludf.DUMMYFUNCTION("MIN(FILTER('Cleaned data'!O:O, 'Cleaned data'!E:E=B32))"),792.0) -> 792 | M32: =IFERROR(__xludf.DUMMYFUNCTION("INDEX(FILTER('Cleaned data'!B:B, ('Cleaned data'!E:E=B32)*'Cleaned data'!O:O=MIN(FILTER('Cleaned data'!O:O, 'Cleaned data'!E:E=B32))))"),"Union Pacific Corp") -> Union Pacific Corp | N32: =IFERROR(__xludf.DUMMYFUNCTION("MAX(FILTER('Cleaned data'!O:O, 'Cleaned data'!E:E=B32))"),1178.0) -> 1178 | O32: =IFERROR(__xludf.DUMMYFUNCTION("INDEX(FILTER('Cleaned data'!B:B, ('Cleaned data'!E:E=B32)*'Cleaned data'!O:O=MAX(FILTER('Cleaned data'!O:O, 'Cleaned data'!E:E=B32))))"),"XPO Logistics Inc") -> XPO Logistics Inc | P32: =IFERROR(__xludf.DUMMYFUNCTION("MEDIAN(FILTER('Cleaned data'!O:O, 'Cleaned data'!E:E=B32))"),1145.5) -> 1145.5 | Q32: =N32-L32 -> 386
A33: =COUNTIF('Cleaned data'!E:E, B33) -> 5 | B33: Trading Companies and Distributors | C33: =IFERROR(__xludf.DUMMYFUNCTION("MIN(FILTER('Cleaned data'!L:L, 'Cleaned data'!E:E=B33))"),230.0) -> 230 | D33: =IFERROR(__xludf.DUMMYFUNCTION("MAX(FILTER('Cleaned data'!L:L, 'Cleaned data'!E:E=B33))"),477.0) -> 477 | E33: =IFERROR(__xludf.DUMMYFUNCTION("MEDIAN(FILTER('Cleaned data'!L:L, 'Cleaned data'!E:E=B33))"),255.0) -> 255 | F33: =IFERROR(__xludf.DUMMYFUNCTION("MIN(FILTER('Cleaned data'!M:M, 'Cleaned data'!E:E=B33))"),201.0) -> 201 | G33: =IFERROR(__xludf.DUMMYFUNCTION("MAX(FILTER('Cleaned data'!M:M, 'Cleaned data'!E:E=B33))"),385.0) -> 385 | H33: =IFERROR(__xludf.DUMMYFUNCTION("MEDIAN(FILTER('Cleaned data'!M:M, 'Cleaned data'!E:E=B33))"),306.0) -> 306 | I33: =IFERROR(__xludf.DUMMYFUNCTION("MIN(FILTER('Cleaned data'!N:N,'Cleaned data'!E:E=B33))"),200.0) -> 200 | J33: =IFERROR(__xludf.DUMMYFUNCTION("MAX(FILTER('Cleaned data'!N:N,'Cleaned data'!E:E=B33))"),300.0) -> 300 | K33: =IFERROR(__xludf.DUMMYFUNCTION("MEDIAN(FILTER('Cleaned data'!N:N, 'Cleaned data'!E:E=B33))"),240.0) -> 240 | L33: =IFERROR(__xludf.DUMMYFUNCTION("MIN(FILTER('Cleaned data'!O:O, 'Cleaned data'!E:E=B33))"),641.0) -> 641 | M33: =IFERROR(__xludf.DUMMYFUNCTION("INDEX(FILTER('Cleaned data'!B:B, ('Cleaned data'!E:E=B33)*'Cleaned data'!O:O=MIN(FILTER('Cleaned data'!O:O, 'Cleaned data'!E:E=B33))))"),"Euro Tech Holdings Company Ltd") -> Euro Tech Holdings Company Ltd | N33: =IFERROR(__xludf.DUMMYFUNCTION("MAX(FILTER('Cleaned data'!O:O, 'Cleaned data'!E:E=B33))"),1090.0) -> 1090 | O33: =IFERROR(__xludf.DUMMYFUNCTION("INDEX(FILTER('Cleaned data'!B:B, ('Cleaned data'!E:E=B33)*'Cleaned data'!O:O=MAX(FILTER('Cleaned data'!O:O, 'Cleaned data'!E:E=B33))))"),"United Rentals Inc") -> United Rentals Inc | P33: =IFERROR(__xludf.DUMMYFUNCTION("MEDIAN(FILTER('Cleaned data'!O:O, 'Cleaned data'!E:E=B33))"),880.0) -> 880 | Q33: =N33-L33 -> 449
A34: =COUNTIF('Cleaned data'!E:E, B34) -> 4 | B34: Beverages | C34: =IFERROR(__xludf.DUMMYFUNCTION("MIN(FILTER('Cleaned data'!L:L, 'Cleaned data'!E:E=B34))"),200.0) -> 200 | D34: =IFERROR(__xludf.DUMMYFUNCTION("MAX(FILTER('Cleaned data'!L:L, 'Cleaned data'!E:E=B34))"),719.0) -> 719 | E34: =IFERROR(__xludf.DUMMYFUNCTION("MEDIAN(FILTER('Cleaned data'!L:L, 'Cleaned data'!E:E=B34))"),487.0) -> 487 | F34: =IFERROR(__xludf.DUMMYFUNCTION("MIN(FILTER('Cleaned data'!M:M, 'Cleaned data'!E:E=B34))"),201.0) -> 201 | G34: =IFERROR(__xludf.DUMMYFUNCTION("MAX(FILTER('Cleaned data'!M:M, 'Cleaned data'!E:E=B34))"),344.0) -> 344 | H34: =IFERROR(__xludf.DUMMYFUNCTION("MEDIAN(FILTER('Cleaned data'!M:M, 'Cleaned data'!E:E=B34))"),326.5) -> 326.5 | I34: =IFERROR(__xludf.DUMMYFUNCTION("MIN(FILTER('Cleaned data'!N:N,'Cleaned data'!E:E=B34))"),200.0) -> 200 | J34: =IFERROR(__xludf.DUMMYFUNCTION("MAX(FILTER('Cleaned data'!N:N,'Cleaned data'!E:E=B34))"),358.0) -> 358 | K34: =IFERROR(__xludf.DUMMYFUNCTION("MEDIAN(FILTER('Cleaned data'!N:N, 'Cleaned data'!E:E=B34))"),297.5) -> 297.5 | L34: =IFERROR(__xludf.DUMMYFUNCTION("MIN(FILTER('Cleaned data'!O:O, 'Cleaned data'!E:E=B34))"),601.0) -> 601 | M34: =IFERROR(__xludf.DUMMYFUNCTION("INDEX(FILTER('Cleaned data'!B:B, ('Cleaned data'!E:E=B34)*'Cleaned data'!O:O=MIN(FILTER('Cleaned data'!O:O, 'Cleaned data'!E:E=B34))))"),"Coca-Cola Co") -> Coca-Cola Co | N34: =IFERROR(__xludf.DUMMYFUNCTION("MAX(FILTER('Cleaned data'!O:O, 'Cleaned data'!E:E=B34))"),1417.0) -> 1417 | O34: =IFERROR(__xludf.DUMMYFUNCTION("INDEX(FILTER('Cleaned data'!B:B, ('Cleaned data'!E:E=B34)*'Cleaned data'!O:O=MAX(FILTER('Cleaned data'!O:O, 'Cleaned data'!E:E=B34))))"),"PepsiCo Inc") -> PepsiCo Inc | P34: =IFERROR(__xludf.DUMMYFUNCTION("MEDIAN(FILTER('Cleaned data'!O:O, 'Cleaned data'!E:E=B34))"),1113.0) -> 1113 | Q34: =N34-L34 -> 816
A35: =COUNTIF('Cleaned data'!E:E, B35) -> 4 | B35: Automobiles | C35: =IFERROR(__xludf.DUMMYFUNCTION("MIN(FILTER('Cleaned data'!L:L, 'Cleaned data'!E:E=B35))"),215.0) -> 215 | D35: =IFERROR(__xludf.DUMMYFUNCTION("MAX(FILTER('Cleaned data'!L:L, 'Cleaned data'!E:E=B35))"),555.0) -> 555 | E35: =IFERROR(__xludf.DUMMYFUNCTION("MEDIAN(FILTER('Cleaned data'!L:L, 'Cleaned data'!E:E=B35))"),401.0) -> 401 | F35: =IFERROR(__xludf.DUMMYFUNCTION("MIN(FILTER('Cleaned data'!M:M, 'Cleaned data'!E:E=B35))"),160.0) -> 160 | G35: =IFERROR(__xludf.DUMMYFUNCTION("MAX(FILTER('Cleaned data'!M:M, 'Cleaned data'!E:E=B35))"),303.0) -> 303 | H35: =IFERROR(__xludf.DUMMYFUNCTION("MEDIAN(FILTER('Cleaned data'!M:M, 'Cleaned data'!E:E=B35))"),227.0) -> 227 | I35: =IFERROR(__xludf.DUMMYFUNCTION("MIN(FILTER('Cleaned data'!N:N,'Cleaned data'!E:E=B35))"),200.0) -> 200 | J35: =IFERROR(__xludf.DUMMYFUNCTION("MAX(FILTER('Cleaned data'!N:N,'Cleaned data'!E:E=B35))"),278.0) -> 278 | K35: =IFERROR(__xludf.DUMMYFUNCTION("MEDIAN(FILTER('Cleaned data'!N:N, 'Cleaned data'!E:E=B35))"),235.0) -> 235 | L35: =IFERROR(__xludf.DUMMYFUNCTION("MIN(FILTER('Cleaned data'!O:O, 'Cleaned data'!E:E=B35))"),623.0) -> 623 | M35: =IFERROR(__xludf.DUMMYFUNCTION("INDEX(FILTER('Cleaned data'!B:B, ('Cleaned data'!E:E=B35)*'Cleaned data'!O:O=MIN(FILTER('Cleaned data'!O:O, 'Cleaned data'!E:E=B35))))"),"Xpeng Inc") -> Xpeng Inc | N35: =IFERROR(__xludf.DUMMYFUNCTION("MAX(FILTER('Cleaned data'!O:O, 'Cleaned data'!E:E=B35))"),1068.0) -> 1068 | O35: =IFERROR(__xludf.DUMMYFUNCTION("INDEX(FILTER('Cleaned data'!B:B, ('Cleaned data'!E:E=B35)*'Cleaned data'!O:O=MAX(FILTER('Cleaned data'!O:O, 'Cleaned data'!E:E=B35))))"),"General Motors Co") -> General Motors Co | P35: =IFERROR(__xludf.DUMMYFUNCTION("MEDIAN(FILTER('Cleaned data'!O:O, 'Cleaned data'!E:E=B35))"),873.0) -> 873 | Q35: =N35-L35 -> 445
A36: =COUNTIF('Cleaned data'!E:E, B36) -> 4 | B36: Packaging | C36: =IFERROR(__xludf.DUMMYFUNCTION("MIN(FILTER('Cleaned data'!L:L, 'Cleaned data'!E:E=B36))"),500.0) -> 500 | D36: =IFERROR(__xludf.DUMMYFUNCTION("MAX(FILTER('Cleaned data'!L:L, 'Cleaned data'!E:E=B36))"),555.0) -> 555 | E36: =IFERROR(__xludf.DUMMYFUNCTION("MEDIAN(FILTER('Cleaned data'!L:L, 'Cleaned data'!E:E=B36))"),545.0) -> 545 | F36: =IFERROR(__xludf.DUMMYFUNCTION("MIN(FILTER('Cleaned data'!M:M, 'Cleaned data'!E:E=B36))"),303.0) -> 303 | G36: =IFERROR(__xludf.DUMMYFUNCTION("MAX(FILTER('Cleaned data'!M:M, 'Cleaned data'!E:E=B36))"),347.0) -> 347 | H36: =IFERROR(__xludf.DUMMYFUNCTION("MEDIAN(FILTER('Cleaned data'!M:M, 'Cleaned data'!E:E=B36))"),321.0) -> 321 | I36: =IFERROR(__xludf.DUMMYFUNCTION("MIN(FILTER('Cleaned data'!N:N,'Cleaned data'!E:E=B36))"),257.0) -> 257 | J36: =IFERROR(__xludf.DUMMYFUNCTION("MAX(FILTER('Cleaned data'!N:N,'Cleaned data'!E:E=B36))"),325.0) -> 325 | K36: =IFERROR(__xludf.DUMMYFUNCTION("MEDIAN(FILTER('Cleaned data'!N:N, 'Cleaned data'!E:E=B36))"),302.5) -> 302.5 | L36: =IFERROR(__xludf.DUMMYFUNCTION("MIN(FILTER('Cleaned data'!O:O, 'Cleaned data'!E:E=B36))"),1103.0) -> 1103 | M36: =IFERROR(__xludf.DUMMYFUNCTION("INDEX(FILTER('Cleaned data'!B:B, ('Cleaned data'!E:E=B36)*'Cleaned data'!O:O=MIN(FILTER('Cleaned data'!O:O, 'Cleaned data'!E:E=B36))))"),"Packaging Corp of America") -> Packaging Corp of America | N36: =IFERROR(__xludf.DUMMYFUNCTION("MAX(FILTER('Cleaned data'!O:O, 'Cleaned data'!E:E=B36))"),1207.0) -> 1207 | O36: =IFERROR(__xludf.DUMMYFUNCTION("INDEX(FILTER('Cleaned data'!B:B, ('Cleaned data'!E:E=B36)*'Cleaned data'!O:O=MAX(FILTER('Cleaned data'!O:O, 'Cleaned data'!E:E=B36))))"),"Avery Dennison Corp") -> Avery Dennison Corp | P36: =IFERROR(__xludf.DUMMYFUNCTION("MEDIAN(FILTER('Cleaned data'!O:O, 'Cleaned data'!E:E=B36))"),1157.0) -> 1157 | Q36: =N36-L36 -> 104
A37: =COUNTIF('Cleaned data'!E:E, B37) -> 3 | B37: Auto Components | C37: =IFERROR(__xludf.DUMMYFUNCTION("MIN(FILTER('Cleaned data'!L:L, 'Cleaned data'!E:E=B37))"),200.0) -> 200 | D37: =IFERROR(__xludf.DUMMYFUNCTION("MAX(FILTER('Cleaned data'!L:L, 'Cleaned data'!E:E=B37))"),555.0) -> 555 | E37: =IFERROR(__xludf.DUMMYFUNCTION("MEDIAN(FILTER('Cleaned data'!L:L, 'Cleaned data'!E:E=B37))"),260.0) -> 260 | F37: =IFERROR(__xludf.DUMMYFUNCTION("MIN(FILTER('Cleaned data'!M:M, 'Cleaned data'!E:E=B37))"),200.0) -> 200 | G37: =IFERROR(__xludf.DUMMYFUNCTION("MAX(FILTER('Cleaned data'!M:M, 'Cleaned data'!E:E=B37))"),339.0) -> 339 | H37: =IFERROR(__xludf.DUMMYFUNCTION("MEDIAN(FILTER('Cleaned data'!M:M, 'Cleaned data'!E:E=B37))"),206.0) -> 206 | I37: =IFERROR(__xludf.DUMMYFUNCTION("MIN(FILTER('Cleaned data'!N:N,'Cleaned data'!E:E=B37))"),200.0) -> 200 | J37: =IFERROR(__xludf.DUMMYFUNCTION("MAX(FILTER('Cleaned data'!N:N,'Cleaned data'!E:E=B37))"),310.0) -> 310 | K37: =IFERROR(__xludf.DUMMYFUNCTION("MEDIAN(FILTER('Cleaned data'!N:N, 'Cleaned data'!E:E=B37))"),230.0) -> 230 | L37: =IFERROR(__xludf.DUMMYFUNCTION("MIN(FILTER('Cleaned data'!O:O, 'Cleaned data'!E:E=B37))"),600.0) -> 600 | M37: =IFERROR(__xludf.DUMMYFUNCTION("INDEX(FILTER('Cleaned data'!B:B, ('Cleaned data'!E:E=B37)*'Cleaned data'!O:O=MIN(FILTER('Cleaned data'!O:O, 'Cleaned data'!E:E=B37))))"),"XL Fleet Corp") -> XL Fleet Corp | N37: =IFERROR(__xludf.DUMMYFUNCTION("MAX(FILTER('Cleaned data'!O:O, 'Cleaned data'!E:E=B37))"),1204.0) -> 1204 | O37: =IFERROR(__xludf.DUMMYFUNCTION("INDEX(FILTER('Cleaned data'!B:B, ('Cleaned data'!E:E=B37)*'Cleaned data'!O:O=MAX(FILTER('Cleaned data'!O:O, 'Cleaned data'!E:E=B37))))"),"Aptiv PLC") -> Aptiv PLC | P37: =IFERROR(__xludf.DUMMYFUNCTION("MEDIAN(FILTER('Cleaned data'!O:O, 'Cleaned data'!E:E=B37))"),696.0) -> 696 | Q37: =N37-L37 -> 604
A38: =COUNTIF('Cleaned data'!E:E, B38) -> 3 | B38: Telecommunication | C38: =IFERROR(__xludf.DUMMYFUNCTION("MIN(FILTER('Cleaned data'!L:L, 'Cleaned data'!E:E=B38))"),210.0) -> 210 | D38: =IFERROR(__xludf.DUMMYFUNCTION("MAX(FILTER('Cleaned data'!L:L, 'Cleaned data'!E:E=B38))"),535.0) -> 535 | E38: =IFERROR(__xludf.DUMMYFUNCTION("MEDIAN(FILTER('Cleaned data'!L:L, 'Cleaned data'!E:E=B38))"),342.0) -> 342 | F38: =IFERROR(__xludf.DUMMYFUNCTION("MIN(FILTER('Cleaned data'!M:M, 'Cleaned data'!E:E=B38))"),200.0) -> 200 | G38: =IFERROR(__xludf.DUMMYFUNCTION("MAX(FILTER('Cleaned data'!M:M, 'Cleaned data'!E:E=B38))"),331.0) -> 331 | H38: =IFERROR(__xludf.DUMMYFUNCTION("MEDIAN(FILTER('Cleaned data'!M:M, 'Cleaned data'!E:E=B38))"),327.0) -> 327 | I38: =IFERROR(__xludf.DUMMYFUNCTION("MIN(FILTER('Cleaned data'!N:N,'Cleaned data'!E:E=B38))"),230.0) -> 230 | J38: =IFERROR(__xludf.DUMMYFUNCTION("MAX(FILTER('Cleaned data'!N:N,'Cleaned data'!E:E=B38))"),305.0) -> 305 | K38: =IFERROR(__xludf.DUMMYFUNCTION("MEDIAN(FILTER('Cleaned data'!N:N, 'Cleaned data'!E:E=B38))"),305.0) -> 305 | L38: =IFERROR(__xludf.DUMMYFUNCTION("MIN(FILTER('Cleaned data'!O:O, 'Cleaned data'!E:E=B38))"),715.0) -> 715 | M38: =IFERROR(__xludf.DUMMYFUNCTION("INDEX(FILTER('Cleaned data'!B:B, ('Cleaned data'!E:E=B38)*'Cleaned data'!O:O=MIN(FILTER('Cleaned data'!O:O, 'Cleaned data'!E:E=B38))))"),"AT&T Inc") -> AT&T Inc | N38: =IFERROR(__xludf.DUMMYFUNCTION("MAX(FILTER('Cleaned data'!O:O, 'Cleaned data'!E:E=B38))"),1167.0) -> 1167 | O38: =IFERROR(__xludf.DUMMYFUNCTION("INDEX(FILTER('Cleaned data'!B:B, ('Cleaned data'!E:E=B38)*'Cleaned data'!O:O=MAX(FILTER('Cleaned data'!O:O, 'Cleaned data'!E:E=B38))))"),"Lumen Technologies Inc") -> Lumen Technologies Inc | P38: =IFERROR(__xludf.DUMMYFUNCTION("MEDIAN(FILTER('Cleaned data'!O:O, 'Cleaned data'!E:E=B38))"),903.0) -> 903 | Q38: =N38-L38 -> 452
A39: =COUNTIF('Cleaned data'!E:E, B39) -> 3 | B39: Marine | C39: =IFERROR(__xludf.DUMMYFUNCTION("MIN(FILTER('Cleaned data'!L:L, 'Cleaned data'!E:E=B39))"),242.0) -> 242 | D39: =IFERROR(__xludf.DUMMYFUNCTION("MAX(FILTER('Cleaned data'!L:L, 'Cleaned data'!E:E=B39))"),345.0) -> 345 | E39: =IFERROR(__xludf.DUMMYFUNCTION("MEDIAN(FILTER('Cleaned data'!L:L, 'Cleaned data'!E:E=B39))"),329.0) -> 329 | F39: =IFERROR(__xludf.DUMMYFUNCTION("MIN(FILTER('Cleaned data'!M:M, 'Cleaned data'!E:E=B39))"),204.0) -> 204 | G39: =IFERROR(__xludf.DUMMYFUNCTION("MAX(FILTER('Cleaned data'!M:M, 'Cleaned data'!E:E=B39))"),351.0) -> 351 | H39: =IFERROR(__xludf.DUMMYFUNCTION("MEDIAN(FILTER('Cleaned data'!M:M, 'Cleaned data'!E:E=B39))"),300.0) -> 300 | I39: =IFERROR(__xludf.DUMMYFUNCTION("MIN(FILTER('Cleaned data'!N:N,'Cleaned data'!E:E=B39))"),200.0) -> 200 | J39: =IFERROR(__xludf.DUMMYFUNCTION("MAX(FILTER('Cleaned data'!N:N,'Cleaned data'!E:E=B39))"),320.0) -> 320 | K39: =IFERROR(__xludf.DUMMYFUNCTION("MEDIAN(FILTER('Cleaned data'!N:N, 'Cleaned data'!E:E=B39))"),305.0) -> 305 | L39: =IFERROR(__xludf.DUMMYFUNCTION("MIN(FILTER('Cleaned data'!O:O, 'Cleaned data'!E:E=B39))"),646.0) -> 646 | M39: =IFERROR(__xludf.DUMMYFUNCTION("INDEX(FILTER('Cleaned data'!B:B, ('Cleaned data'!E:E=B39)*'Cleaned data'!O:O=MIN(FILTER('Cleaned data'!O:O, 'Cleaned data'!E:E=B39))))"),"Costamare Inc") -> Costamare Inc | N39: =IFERROR(__xludf.DUMMYFUNCTION("MAX(FILTER('Cleaned data'!O:O, 'Cleaned data'!E:E=B39))"),1000.0) -> 1000 | O39: =IFERROR(__xludf.DUMMYFUNCTION("INDEX(FILTER('Cleaned data'!B:B, ('Cleaned data'!E:E=B39)*'Cleaned data'!O:O=MAX(FILTER('Cleaned data'!O:O, 'Cleaned data'!E:E=B39))))"),"ZIM Integrated Shipping Services Ltd") -> ZIM Integrated Shipping Services Ltd | P39: =IFERROR(__xludf.DUMMYFUNCTION("MEDIAN(FILTER('Cleaned data'!O:O, 'Cleaned data'!E:E=B39))"),950.0) -> 950 | Q39: =N39-L39 -> 354
A40: =COUNTIF('Cleaned data'!E:E, B40) -> 3 | B40: Diversified Consumer Services | C40: =IFERROR(__xludf.DUMMYFUNCTION("MIN(FILTER('Cleaned data'!L:L, 'Cleaned data'!E:E=B40))"),203.0) -> 203 | D40: =IFERROR(__xludf.DUMMYFUNCTION("MAX(FILTER('Cleaned data'!L:L, 'Cleaned data'!E:E=B40))"),365.0) -> 365 | E40: =IFERROR(__xludf.DUMMYFUNCTION("MEDIAN(FILTER('Cleaned data'!L:L, 'Cleaned data'!E:E=B40))"),290.0) -> 290 | F40: =IFERROR(__xludf.DUMMYFUNCTION("MIN(FILTER('Cleaned data'!M:M, 'Cleaned data'!E:E=B40))"),200.0) -> 200 | G40: =IFERROR(__xludf.DUMMYFUNCTION("MAX(FILTER('Cleaned data'!M:M, 'Cleaned data'!E:E=B40))"),297.0) -> 297 | H40: =IFERROR(__xludf.DUMMYFUNCTION("MEDIAN(FILTER('Cleaned data'!M:M, 'Cleaned data'!E:E=B40))"),203.0) -> 203 | I40: =IFERROR(__xludf.DUMMYFUNCTION("MIN(FILTER('Cleaned data'!N:N,'Cleaned data'!E:E=B40))"),205.0) -> 205 | J40: =IFERROR(__xludf.DUMMYFUNCTION("MAX(FILTER('Cleaned data'!N:N,'Cleaned data'!E:E=B40))"),250.0) -> 250 | K40: =IFERROR(__xludf.DUMMYFUNCTION("MEDIAN(FILTER('Cleaned data'!N:N, 'Cleaned data'!E:E=B40))"),205.0) -> 205 | L40: =IFERROR(__xludf.DUMMYFUNCTION("MIN(FILTER('Cleaned data'!O:O, 'Cleaned data'!E:E=B40))"),608.0) -> 608 | M40: =IFERROR(__xludf.DUMMYFUNCTION("INDEX(FILTER('Cleaned data'!B:B, ('Cleaned data'!E:E=B40)*'Cleaned data'!O:O=MIN(FILTER('Cleaned data'!O:O, 'Cleaned data'!E:E=B40))))"),"ATA Creativity Global") -> ATA Creativity Global | N40: =IFERROR(__xludf.DUMMYFUNCTION("MAX(FILTER('Cleaned data'!O:O, 'Cleaned data'!E:E=B40))"),912.0) -> 912 | O40: =IFERROR(__xludf.DUMMYFUNCTION("INDEX(FILTER('Cleaned data'!B:B, ('Cleaned data'!E:E=B40)*'Cleaned data'!O:O=MAX(FILTER('Cleaned data'!O:O, 'Cleaned data'!E:E=B40))))"),"Perdoceo Education Corp") -> Perdoceo Education Corp | P40: =IFERROR(__xludf.DUMMYFUNCTION("MEDIAN(FILTER('Cleaned data'!O:O, 'Cleaned data'!E:E=B40))"),698.0) -> 698 | Q40: =N40-L40 -> 304
A41: =COUNTIF('Cleaned data'!E:E, B41) -> 3 | B41: Leisure Products | C41: =IFERROR(__xludf.DUMMYFUNCTION("MIN(FILTER('Cleaned data'!L:L, 'Cleaned data'!E:E=B41))"),233.0) -> 233 | D41: =IFERROR(__xludf.DUMMYFUNCTION("MAX(FILTER('Cleaned data'!L:L, 'Cleaned data'!E:E=B41))"),269.0) -> 269 | E41: =IFERROR(__xludf.DUMMYFUNCTION("MEDIAN(FILTER('Cleaned data'!L:L, 'Cleaned data'!E:E=B41))"),255.0) -> 255 | F41: =IFERROR(__xludf.DUMMYFUNCTION("MIN(FILTER('Cleaned data'!M:M, 'Cleaned data'!E:E=B41))"),224.0) -> 224 | G41: =IFERROR(__xludf.DUMMYFUNCTION("MAX(FILTER('Cleaned data'!M:M, 'Cleaned data'!E:E=B41))"),301.0) -> 301 | H41: =IFERROR(__xludf.DUMMYFUNCTION("MEDIAN(FILTER('Cleaned data'!M:M, 'Cleaned data'!E:E=B41))"),253.0) -> 253 | I41: =IFERROR(__xludf.DUMMYFUNCTION("MIN(FILTER('Cleaned data'!N:N,'Cleaned data'!E:E=B41))"),200.0) -> 200 | J41: =IFERROR(__xludf.DUMMYFUNCTION("MAX(FILTER('Cleaned data'!N:N,'Cleaned data'!E:E=B41))"),305.0) -> 305 | K41: =IFERROR(__xludf.DUMMYFUNCTION("MEDIAN(FILTER('Cleaned data'!N:N, 'Cleaned data'!E:E=B41))"),300.0) -> 300 | L41: =IFERROR(__xludf.DUMMYFUNCTION("MIN(FILTER('Cleaned data'!O:O, 'Cleaned data'!E:E=B41))"),657.0) -> 657 | M41: =IFERROR(__xludf.DUMMYFUNCTION("INDEX(FILTER('Cleaned data'!B:B, ('Cleaned data'!E:E=B41)*'Cleaned data'!O:O=MIN(FILTER('Cleaned data'!O:O, 'Cleaned data'!E:E=B41))))"),"Ammo Inc") -> Ammo Inc | N41: =IFERROR(__xludf.DUMMYFUNCTION("MAX(FILTER('Cleaned data'!O:O, 'Cleaned data'!E:E=B41))"),856.0) -> 856 | O41: =IFERROR(__xludf.DUMMYFUNCTION("INDEX(FILTER('Cleaned data'!B:B, ('Cleaned data'!E:E=B41)*'Cleaned data'!O:O=MAX(FILTER('Cleaned data'!O:O, 'Cleaned data'!E:E=B41))))"),"Hasbro Inc") -> Hasbro Inc | P41: =IFERROR(__xludf.DUMMYFUNCTION("MEDIAN(FILTER('Cleaned data'!O:O, 'Cleaned data'!E:E=B41))"),827.0) -> 827 | Q41: =N41-L41 -> 199
A42: =COUNTIF('Cleaned data'!E:E, B42) -> 3 | B42: Distributors | C42: =IFERROR(__xludf.DUMMYFUNCTION("MIN(FILTER('Cleaned data'!L:L, 'Cleaned data'!E:E=B42))"),515.0) -> 515 | D42: =IFERROR(__xludf.DUMMYFUNCTION("MAX(FILTER('Cleaned data'!L:L, 'Cleaned data'!E:E=B42))"),535.0) -> 535 | E42: =IFERROR(__xludf.DUMMYFUNCTION("MEDIAN(FILTER('Cleaned data'!L:L, 'Cleaned data'!E:E=B42))"),525.0) -> 525 | F42: =IFERROR(__xludf.DUMMYFUNCTION("MIN(FILTER('Cleaned data'!M:M, 'Cleaned data'!E:E=B42))"),225.0) -> 225 | G42: =IFERROR(__xludf.DUMMYFUNCTION("MAX(FILTER('Cleaned data'!M:M, 'Cleaned data'!E:E=B42))"),306.0) -> 306 | H42: =IFERROR(__xludf.DUMMYFUNCTION("MEDIAN(FILTER('Cleaned data'!M:M, 'Cleaned data'!E:E=B42))"),300.0) -> 300 | I42: =IFERROR(__xludf.DUMMYFUNCTION("MIN(FILTER('Cleaned data'!N:N,'Cleaned data'!E:E=B42))"),305.0) -> 305 | J42: =IFERROR(__xludf.DUMMYFUNCTION("MAX(FILTER('Cleaned data'!N:N,'Cleaned data'!E:E=B42))"),313.0) -> 313 | K42: =IFERROR(__xludf.DUMMYFUNCTION("MEDIAN(FILTER('Cleaned data'!N:N, 'Cleaned data'!E:E=B42))"),305.0) -> 305 | L42: =IFERROR(__xludf.DUMMYFUNCTION("MIN(FILTER('Cleaned data'!O:O, 'Cleaned data'!E:E=B42))"),1065.0) -> 1065 | M42: =IFERROR(__xludf.DUMMYFUNCTION("INDEX(FILTER('Cleaned data'!B:B, ('Cleaned data'!E:E=B42)*'Cleaned data'!O:O=MIN(FILTER('Cleaned data'!O:O, 'Cleaned data'!E:E=B42))))"),"Genuine Parts Co") -> Genuine Parts Co | N42: =IFERROR(__xludf.DUMMYFUNCTION("MAX(FILTER('Cleaned data'!O:O, 'Cleaned data'!E:E=B42))"),1144.0) -> 1144 | O42: =IFERROR(__xludf.DUMMYFUNCTION("INDEX(FILTER('Cleaned data'!B:B, ('Cleaned data'!E:E=B42)*'Cleaned data'!O:O=MAX(FILTER('Cleaned data'!O:O, 'Cleaned data'!E:E=B42))))"),"Pool Corp") -> Pool Corp | P42: =IFERROR(__xludf.DUMMYFUNCTION("MEDIAN(FILTER('Cleaned data'!O:O, 'Cleaned data'!E:E=B42))"),1120.0) -> 1120 | Q42: =N42-L42 -> 79
A43: =COUNTIF('Cleaned data'!E:E, B43) -> 3 | B43: Industrial Conglomerates | C43: =IFERROR(__xludf.DUMMYFUNCTION("MIN(FILTER('Cleaned data'!L:L, 'Cleaned data'!E:E=B43))"),526.0) -> 526 | D43: =IFERROR(__xludf.DUMMYFUNCTION("MAX(FILTER('Cleaned data'!L:L, 'Cleaned data'!E:E=B43))"),545.0) -> 545 | E43: =IFERROR(__xludf.DUMMYFUNCTION("MEDIAN(FILTER('Cleaned data'!L:L, 'Cleaned data'!E:E=B43))"),533.0) -> 533 | F43: =IFERROR(__xludf.DUMMYFUNCTION("MIN(FILTER('Cleaned data'!M:M, 'Cleaned data'!E:E=B43))"),300.0) -> 300 | G43: =IFERROR(__xludf.DUMMYFUNCTION("MAX(FILTER('Cleaned data'!M:M, 'Cleaned data'!E:E=B43))"),344.0) -> 344 | H43: =IFERROR(__xludf.DUMMYFUNCTION("MEDIAN(FILTER('Cleaned data'!M:M, 'Cleaned data'!E:E=B43))"),310.0) -> 310 | I43: =IFERROR(__xludf.DUMMYFUNCTION("MIN(FILTER('Cleaned data'!N:N,'Cleaned data'!E:E=B43))"),300.0) -> 300 | J43: =IFERROR(__xludf.DUMMYFUNCTION("MAX(FILTER('Cleaned data'!N:N,'Cleaned data'!E:E=B43))"),308.0) -> 308 | K43: =IFERROR(__xludf.DUMMYFUNCTION("MEDIAN(FILTER('Cleaned data'!N:N, 'Cleaned data'!E:E=B43))"),305.0) -> 305 | L43: =IFERROR(__xludf.DUMMYFUNCTION("MIN(FILTER('Cleaned data'!O:O, 'Cleaned data'!E:E=B43))"),1133.0) -> 1133 | M43: =IFERROR(__xludf.DUMMYFUNCTION("INDEX(FILTER('Cleaned data'!B:B, ('Cleaned data'!E:E=B43)*'Cleaned data'!O:O=MIN(FILTER('Cleaned data'!O:O, 'Cleaned data'!E:E=B43))))"),"General Electric Co") -> General Electric Co | N43: =IFERROR(__xludf.DUMMYFUNCTION("MAX(FILTER('Cleaned data'!O:O, 'Cleaned data'!E:E=B43))"),1197.0) -> 1197 | O43: =IFERROR(__xludf.DUMMYFUNCTION("INDEX(FILTER('Cleaned data'!B:B, ('Cleaned data'!E:E=B43)*'Cleaned data'!O:O=MAX(FILTER('Cleaned data'!O:O, 'Cleaned data'!E:E=B43))))"),"Honeywell International Inc") -> Honeywell International Inc | P43: =IFERROR(__xludf.DUMMYFUNCTION("MEDIAN(FILTER('Cleaned data'!O:O, 'Cleaned data'!E:E=B43))"),1141.0) -> 1141 | Q43: =N43-L43 -> 64
A44: =COUNTIF('Cleaned data'!E:E, B44) -> 2 | B44: Tobacco | C44: =IFERROR(__xludf.DUMMYFUNCTION("MIN(FILTER('Cleaned data'!L:L, 'Cleaned data'!E:E=B44))"),500.0) -> 500 | D44: =IFERROR(__xludf.DUMMYFUNCTION("MAX(FILTER('Cleaned data'!L:L, 'Cleaned data'!E:E=B44))"),520.0) -> 520 | E44: =IFERROR(__xludf.DUMMYFUNCTION("MEDIAN(FILTER('Cleaned data'!L:L, 'Cleaned data'!E:E=B44))"),510.0) -> 510 | F44: =IFERROR(__xludf.DUMMYFUNCTION("MIN(FILTER('Cleaned data'!M:M, 'Cleaned data'!E:E=B44))"),327.0) -> 327 | G44: =IFERROR(__xludf.DUMMYFUNCTION("MAX(FILTER('Cleaned data'!M:M, 'Cleaned data'!E:E=B44))"),327.0) -> 327 | H44: =IFERROR(__xludf.DUMMYFUNCTION("MEDIAN(FILTER('Cleaned data'!M:M, 'Cleaned data'!E:E=B44))"),327.0) -> 327 | I44: =IFERROR(__xludf.DUMMYFUNCTION("MIN(FILTER('Cleaned data'!N:N,'Cleaned data'!E:E=B44))"),315.0) -> 315 | J44: =IFERROR(__xludf.DUMMYFUNCTION("MAX(FILTER('Cleaned data'!N:N,'Cleaned data'!E:E=B44))"),341.0) -> 341 | K44: =IFERROR(__xludf.DUMMYFUNCTION("MEDIAN(FILTER('Cleaned data'!N:N, 'Cleaned data'!E:E=B44))"),328.0) -> 328 | L44: =IFERROR(__xludf.DUMMYFUNCTION("MIN(FILTER('Cleaned data'!O:O, 'Cleaned data'!E:E=B44))"),1162.0) -> 1162 | M44: =IFERROR(__xludf.DUMMYFUNCTION("INDEX(FILTER('Cleaned data'!B:B, ('Cleaned data'!E:E=B44)*'Cleaned data'!O:O=MIN(FILTER('Cleaned data'!O:O, 'Cleaned data'!E:E=B44))))"),"Philip Morris International Inc") -> Philip Morris International Inc | N44: =IFERROR(__xludf.DUMMYFUNCTION("MAX(FILTER('Cleaned data'!O:O, 'Cleaned data'!E:E=B44))"),1168.0) -> 1168 | O44: =IFERROR(__xludf.DUMMYFUNCTION("INDEX(FILTER('Cleaned data'!B:B, ('Cleaned data'!E:E=B44)*'Cleaned data'!O:O=MAX(FILTER('Cleaned data'!O:O, 'Cleaned data'!E:E=B44))))"),"Altria Group Inc") -> Altria Group Inc | P44: =IFERROR(__xludf.DUMMYFUNCTION("MEDIAN(FILTER('Cleaned data'!O:O, 'Cleaned data'!E:E=B44))"),1165.0) -> 1165 | Q44: =N44-L44 -> 6

Sheet Difference within industries

Sheet Industry ESG comparison

Sheet Leaders & Laggards
A1: number_of_companies | B1: industry | C1: Total_min_score | D1: total_min_score_company_name | E1: Total_max_score | F1: total_max_score_company_name | G1: total_median_score | H1: total_score_difference
A2: 3 | B2: Leisure Products | C2: 657 | D2: Ammo Inc | E2: 856 | F2: Hasbro Inc | G2: 827 | H2: 199
A3: 3 | B3: Diversified Consumer Services | C3: 608 | D3: ATA Creativity Global | E3: 912 | F3: Perdoceo Education Corp | G3: 698 | H3: 304
A4: 3 | B4: Marine | C4: 646 | D4: Costamare Inc | E4: 1000 | F4: ZIM Integrated Shipping Services Ltd | G4: 950 | H4: 354
A5: 4 | B5: Automobiles | C5: 623 | D5: Xpeng Inc | E5: 1068 | F5: General Motors Co | G5: 873 | H5: 445
A6: 5 | B6: Trading Companies and Distributors | C6: 641 | D6: Euro Tech Holdings Company Ltd | E6: 1090 | F6: United Rentals Inc | G6: 880 | H6: 449
A7: 9 | B7: Textiles Apparel and Luxury Goods | C7: 621 | D7: Ever-Glory International Group Inc | E7: 1106 | F7: VF Corp | G7: 1039 | H7: 485
A8: 7 | B8: Airlines | C8: 629 | D8: United Airlines Holdings Inc | E8: 1128 | F8: Delta Air Lines Inc | G8: 746 | H8: 499
A9: 3 | B9: Distributors | C9: 1065 | D9: Genuine Parts Co | E9: 1144 | F9: Pool Corp | G9: 1120 | H9: 79
A10: 9 | B10: Communications | C10: 636 | D10: F5 Inc | E10: 1157 | F10: Motorola Solutions Inc | G10: 1015 | H10: 521
A11: 3 | B11: Telecommunication | C11: 715 | D11: AT&T Inc | E11: 1167 | F11: Lumen Technologies Inc | G11: 903 | H11: 452
A12: 2 | B12: Tobacco | C12: 1162 | D12: Philip Morris International Inc | E12: 1168 | F12: Altria Group Inc | G12: 1165 | H12: 6
A13: 6 | B13: Road and Rail | C13: 792 | D13: Union Pacific Corp | E13: 1178 | F13: XPO Logistics Inc | G13: 1145.5 | H13: 386
... A44: 21 | B44: Energy | C44: 637 | D44: Chevron Corp | E44: 1536 | F44: Conocophillips | G44: 1148 | H44: 899
A47: Auto Components | B47: 600 | C47: XL Fleet Corp
A48: Banking | B48: 600 | C48: Zions Bancorporation NA
A49: Construction | B49: 600 | C49: Granite Construction Inc
A50: Electrical Equipment | B50: 600 | C50: Corning Inc
A51: Health Care | B51: 600 | C51: Teleflex Inc
A52: Hotels Restaurants and Leisure | B52: 600 | C52: Allied Esports Entertainment Inc
A53: Beverages | B53: 601 | C53: Coca-Cola Co
A54: Biotechnology | B54: 604 | C54: Aadi Bioscience Inc
A55: Media | B55: 607 | C55: Playstudios Inc
A56: Diversified Consumer Services | B56: 608 | C56: ATA Creativity Global
A59: Real Estate | B59: 1363 | C59: Hannon Armstrong Sustainable Infrastructure Capital Inc
A60: Building | B60: 1409 | C60: Trane Technologies PLC
... A68: Energy | B68: 1536 | C68: Conocophillips
